Workbook

Sheet Produtos
A1: COD | B1: Marca | C1: Coleção | D1: Categoria | E1: Produto | F1: Nome | G1: Unidade | H1: Volume | I1: Tipo | J1: Descrição | K1: Preço Custo | L1: Preço Venda | M1: Estoque | N1: Status estoque
A2: NATBRA-2816 | B2: Natura | C2: Tododia | D2: Hidrante Desodorante Corporal | E2: =TRIM(CONCATENATE(D2, " ", C2, " ", F2, " ", IF(G2>0, G2 & "x" & H2, H2), " ", I2)) | F2: Algodão | H2: 400ml | I2: Frasco | J2: Desodorante / nutritivo / creme | K2: 64 | L2: 75.9 | M2: =SUMIF(Movimento!B:B, A2, Movimento!F:F) | N2: =IF(M2=0,"Falta Pedir!",IF(M2<=3,"Baixo Estoque","Em Estoque"))
B3: Natura | C3: Tododia | D3: Hidrante Desodorante Corporal | E3: =TRIM(CONCATENATE(D3, " ", C3, " ", F3, " ", IF(G3>0, G3 & "x" & H3, H3), " ", I3)) | F3: Ameixa e Flor de Baunilha | H3: 400ml | I3: Frasco | J3: Suave de Algodão \ Nutritivo | L3: 75.9 | M3: =SUMIF(Movimento!B:B, A3, Movimento!F:F) | N3: =IF(M3=0,"Falta Pedir!",IF(M3<=3,"Baixo Estoque","Em Estoque"))
B4: Natura | C4: Tododia | D4: Hidrante Desodorante Corporal | E4: =TRIM(CONCATENATE(D4, " ", C4, " ", F4, " ", IF(G4>0, G4 & "x" & H4, H4), " ", I4)) | F4: Acerola e Hibisco | H4: 400ml | I4: Frasco | J4: Refrescante / Gelado | L4: 75.9
B5: Natura | C5: Tododia | D5: Hidrante Desodorante Corporal | E5: =TRIM(CONCATENATE(D5, " ", C5, " ", F5, " ", IF(G5>0, G5 & "x" & H5, H5), " ", I5)) | F5: Amora Vermelha e Jabuticaba | H5: 400ml | I5: Frasco | J5: Desodorante / nutritivo / creme | L5: 75.9
B6: Natura | C6: Tododia | D6: Hidrante Desodorante Corporal | E6: =TRIM(CONCATENATE(D6, " ", C6, " ", F6, " ", IF(G6>0, G6 & "x" & H6, H6), " ", I6)) | F6: Capim Limão e Hortelã | H6: 400ml | I6: Frasco | J6: Desodorante / nutritivo / creme | L6: 75.9
B7: Natura | C7: Tododia | D7: Hidrante Desodorante Corporal | E7: =TRIM(CONCATENATE(D7, " ", C7, " ", F7, " ", IF(G7>0, G7 & "x" & H7, H7), " ", I7)) | F7: Cereja Negra e Praliné | H7: 400ml | I7: Frasco | J7: Desodorante / nutritivo / creme | L7: 75.9
B8: Natura | C8: Tododia | D8: Hidrante Desodorante Corporal | E8: =TRIM(CONCATENATE(D8, " ", C8, " ", F8, " ", IF(G8>0, G8 & "x" & H8, H8), " ", I8)) | F8: Cereja e Avela | H8: 400ml | I8: Frasco | J8: Desodorante / nutritivo / creme | L8: 75.9
B9: Natura | C9: Tododia | D9: Hidrante Desodorante Corporal | E9: =TRIM(CONCATENATE(D9, " ", C9, " ", F9, " ", IF(G9>0, G9 & "x" & H9, H9), " ", I9)) | F9: Cereja e Avela | H9: 400ml | I9: Frasco | J9: HIdrata. Noturno \ Calmante \Chá de Camomila e Lavanda | L9: 75.9
B10: Natura | C10: Tododia | D10: Hidrante Desodorante Corporal | E10: =TRIM(CONCATENATE(D10, " ", C10, " ", F10, " ", IF(G10>0, G10 & "x" & H10, H10), " ", I10)) | F10: Todanoite | H10: 200ml | I10: Frasco | J10: HIdrata. Noturno \ Calmante \ Chá de Camomila e Lavanda | L10: 87.9
B11: Natura | C11: Tododia | D11: Hidrante Desodorante Corporal | E11: =TRIM(CONCATENATE(D11, " ", C11, " ", F11, " ", IF(G11>0, G11 & "x" & H11, H11), " ", I11)) | F11: Flor de Gengibre e Tangerina | H11: 400 ml | I11: Frasco | J11: Nutritivo Energizante | L11: 75.9
B12: Natura | C12: Tododia | D12: Hidrante Desodorante Corporal | E12: =TRIM(CONCATENATE(D12, " ", C12, " ", F12, " ", IF(G12>0, G12 & "x" & H12, H12), " ", I12)) | F12: Flor de Pera e Melissa | H12: 400ml | I12: Frasco | J12: Desodorante / nutritivo / creme | L12: 75.9
B13: Natura | C13: Tododia | D13: Hidrante Desodorante Corporal | E13: =TRIM(CONCATENATE(D13, " ", C13, " ", F13, " ", IF(G13>0, G13 & "x" & H13, H13), " ", I13)) | F13: Framboesa e PImenta Vermelha | H13: 400ml | I13: Frasco | J13: Desodorante / nutritivo / creme | L13: 75.9
B14: Natura | C14: Tododia | D14: Hidrante Desodorante Corporal | E14: =TRIM(CONCATENATE(D14, " ", C14, " ", F14, " ", IF(G14>0, G14 & "x" & H14, H14), " ", I14)) | F14: Jambo Rosa e Flor De Caju | H14: 400ml | I14: Frasco | J14: Desodorante / nutritivo / creme | L14: 75.9
B15: Natura | C15: Tododia | D15: Hidrante Desodorante Corporal | E15: =TRIM(CONCATENATE(D15, " ", C15, " ", F15, " ", IF(G15>0, G15 & "x" & H15, H15), " ", I15)) | F15: Limão Siciliano e Flor de Gardênia | H15: 400ml | I15: Frasco | J15: Desodorante / nutritivo / creme | L15: 75.9
... B23: Natura | C23: Tododia | D23: Hidrante Desodorante Corporal | E23: =TRIM(CONCATENATE(D23, " ", C23, " ", F23, " ", IF(G23>0, G23 & "x" & H23, H23), " ", I23)) | F23: Algodao | H23: 400ml | I23: Refil | J23: Desodorante / nutritivo / creme | L23: 56.4
A24: NATBRA-100423 | B24: Natura | C24: Tododia | D24: Hidrante Desodorante Corporal | E24: =TRIM(CONCATENATE(D24, " ", C24, " ", F24, " ", IF(G24>0, G24 & "x" & H24, H24), " ", I24)) | F24: Ameixa e Flor de Baunilha | H24: 400ml | I24: Refil | J24: Suave de Algodão \ Nutritivo | L24: 56.4
B25: Natura | C25: Tododia | D25: Hidrante Desodorante Corporal | E25: =TRIM(CONCATENATE(D25, " ", C25, " ", F25, " ", IF(G25>0, G25 & "x" & H25, H25), " ", I25)) | F25: Acerola e Hibisco | H25: 400ml | I25: Refil | J25: Refrescante / Gelado | L25: 56.4
B26: Natura | C26: Tododia | D26: Hidrante Desodorante Corporal | E26: =TRIM(CONCATENATE(D26, " ", C26, " ", F26, " ", IF(G26>0, G26 & "x" & H26, H26), " ", I26)) | F26: Amora Vermelha e Jabuticaba | H26: 400ml | I26: Refil | J26: Desodorante / nutritivo / creme | L26: 56.4
A27: NATBRA-190159 | B27: Natura | C27: Tododia | D27: Hidrante Desodorante Corporal | E27: =TRIM(CONCATENATE(D27, " ", C27, " ", F27, " ", IF(G27>0, G27 & "x" & H27, H27), " ", I27)) | F27: Capim Limão e Hortelã | H27: 400ml | I27: Refil | J27: Desodorante / nutritivo / creme | L27: 56.4
B28: Natura | C28: Tododia | D28: Hidrante Desodorante Corporal | E28: =TRIM(CONCATENATE(D28, " ", C28, " ", F28, " ", IF(G28>0, G28 & "x" & H28, H28), " ", I28)) | F28: Cereja Negra e Praliné | H28: 400ml | I28: Refil | J28: Desodorante / nutritivo / creme | L28: 56.4
A29: NATBRA-99137 | B29: Natura | C29: Tododia | D29: Hidrante Desodorante Corporal | E29: =TRIM(CONCATENATE(D29, " ", C29, " ", F29, " ", IF(G29>0, G29 & "x" & H29, H29), " ", I29)) | F29: Cereja e Avela | H29: 400ml | I29: Refil | J29: Desodorante / nutritivo / creme | L29: 56.4
B30: Natura | C30: Tododia | D30: Hidrante Desodorante Corporal | E30: =TRIM(CONCATENATE(D30, " ", C30, " ", F30, " ", IF(G30>0, G30 & "x" & H30, H30), " ", I30)) | F30: Todonoite | H30: 400ml | I30: Refil | J30: Hidrata. Noturno \ calmante | L30: 56.4
B31: Natura | C31: Tododia | D31: Hidrante Desodorante Corporal | E31: =TRIM(CONCATENATE(D31, " ", C31, " ", F31, " ", IF(G31>0, G31 & "x" & H31, H31), " ", I31)) | F31: Todonoite | H31: 200ml | I31: Refil | J31: Hidrata. Noturno \ calmante
A32: NATBRA-152290 | B32: Natura | C32: Tododia | D32: Hidrante Desodorante Corporal | E32: =TRIM(CONCATENATE(D32, " ", C32, " ", F32, " ", IF(G32>0, G32 & "x" & H32, H32), " ", I32)) | F32: Flor de Gengibre e Tangerina | H32: 400ml | I32: Refil | J32: Hidrata. Noturno \ calmante | L32: 56.4
B33: Natura | C33: Tododia | D33: Hidrante Desodorante Corporal | E33: =TRIM(CONCATENATE(D33, " ", C33, " ", F33, " ", IF(G33>0, G33 & "x" & H33, H33), " ", I33)) | F33: Flor de Pera e Melissa | H33: 400ml | I33: Refil | J33: Desodorante / nutritivo / creme | L33: 56.4
B34: Natura | C34: Tododia | D34: Hidrante Desodorante Corporal | E34: =TRIM(CONCATENATE(D34, " ", C34, " ", F34, " ", IF(G34>0, G34 & "x" & H34, H34), " ", I34)) | F34: Framboesa e PImenta Vermelha | H34: 400ml | I34: Refil | J34: Desodorante / nutritivo / creme | L34: 56.4
B35: Natura | C35: Tododia | D35: Hidrante Desodorante Corporal | E35: =TRIM(CONCATENATE(D35, " ", C35, " ", F35, " ", IF(G35>0, G35 & "x" & H35, H35), " ", I35)) | F35: Jambo Rosa e Flor De Caju | H35: 400ml | I35: Refil | J35: Desodorante / nutritivo / creme | L35: 56.4
B36: Natura | C36: Tododia | D36: Hidrante Desodorante Corporal | E36: =TRIM(CONCATENATE(D36, " ", C36, " ", F36, " ", IF(G36>0, G36 & "x" & H36, H36), " ", I36)) | F36: Limão Siciliano e Flor de Gardênia | H36: 400ml | I36: Refil | J36: Nutritivo Energizante | L36: 56.4
B37: Natura | C37: Tododia | D37: Hidrante Desodorante Corporal | E37: =TRIM(CONCATENATE(D37, " ", C37, " ", F37, " ", IF(G37>0, G37 & "x" & H37, H37), " ", I37)) | F37: Macadâmia | H37: 400ml | I37: Refil | J37: Desodorante / nutritivo / creme | L37: 56.4
B38: Natura | C38: Tododia | D38: Hidrante Desodorante Corporal | E38: =TRIM(CONCATENATE(D38, " ", C38, " ", F38, " ", IF(G38>0, G38 & "x" & H38, H38), " ", I38)) | F38: Maça Caramelada e Baunilha | H38: 400ml | I38: Refil | J38: Nutritivo \ Especial São João \ Inspirada na Maçã do Amor | L38: 56.4
B39: Natura | C39: Tododia | D39: Hidrante Desodorante Corporal | E39: =TRIM(CONCATENATE(D39, " ", C39, " ", F39, " ", IF(G39>0, G39 & "x" & H39, H39), " ", I39)) | F39: Manga Rosa e Àgua de Coco | H39: 400ml | I39: Refil | J39: Refrescante / Gelado | L39: 56.4
B40: Natura | C40: Tododia | D40: Hidrante Desodorante Corporal | E40: =TRIM(CONCATENATE(D40, " ", C40, " ", F40, " ", IF(G40>0, G40 & "x" & H40, H40), " ", I40)) | F40: Nóz Pecão e Cacau | H40: 400ml | I40: Refil | J40: Desodorante / nutritivo / creme | L40: 56.4
B41: Natura | C41: Tododia | D41: Hidrante Desodorante Corporal | E41: =TRIM(CONCATENATE(D41, " ", C41, " ", F41, " ", IF(G41>0, G41 & "x" & H41, H41), " ", I41)) | F41: Romã e Flor de Amora | H41: 400ml | I41: Refil | J41: Desodorante / nutritivo / creme | L41: 56.4
B42: Natura | C42: Tododia | D42: Hidrante Desodorante Corporal | E42: =TRIM(CONCATENATE(D42, " ", C42, " ", F42, " ", IF(G42>0, G42 & "x" & H42, H42), " ", I42)) | F42: Tâmara e Canela | H42: 400ml | I42: Refil | J42: Desodorante / nutritivo / creme | L42: 56.4
B43: Natura | C43: Tododia | D43: Creme Hidratante | E43: =TRIM(CONCATENATE(D43, " ", C43, " ", F43, " ", IF(G43>0, G43 & "x" & H43, H43), " ", I43)) | F43: Todonoite | H43: 200ml | I43: Pote | J43: Creme Hidrat. Prebiotica \ Vitam +B5 \ Para Massagem | L43: 81.9
B44: Natura | C44: Tododia | D44: Creme Hidratante | E44: =TRIM(CONCATENATE(D44, " ", C44, " ", F44, " ", IF(G44>0, G44 & "x" & H44, H44), " ", I44)) | F44: Cereja e Avelã | H44: 200ml | I44: Pote | J44: Creme Amanteigado \ Perfumado \ Desodorante
B45: Natura | C45: Tododia | D45: Creme Hidratante | E45: =TRIM(CONCATENATE(D45, " ", C45, " ", F45, " ", IF(G45>0, G45 & "x" & H45, H45), " ", I45)) | F45: Cereja Negra e Praliné | H45: 250g | I45: Pote | J45: Pele Macia \\ Como Veludo \\ HIdrata. e PErfuma 2x Mais | L45: 81.9
B46: Natura | C46: Tododia | D46: Manteiga Creme Corporal | E46: =TRIM(CONCATENATE(D46, " ", C46, " ", F46, " ", IF(G46>0, G46 & "x" & H46, H46), " ", I46)) | F46: Jambo Rosa e Flor De Caju | H46: 200g | I46: Pote | J46: Hidratante / Manteiga para o corpo hidrata \ Uniformiza \ Desodorante | L46: 81.9
B47: Natura | C47: Tododia | D47: Oleo Creme Corporal | E47: =TRIM(CONCATENATE(D47, " ", C47, " ", F47, " ", IF(G47>0, G47 & "x" & H47, H47), " ", I47)) | F47: Jambo Rosa e Flor De Caju | H47: 200ml | I47: Pote | J47: Ultranutritivo \ Restaurador \ Desodorante | L47: 81.9
B48: Natura | C48: Tododia | D48: Oleo Corporal | E48: =TRIM(CONCATENATE(D48, " ", C48, " ", F48, " ", IF(G48>0, G48 & "x" & H48, H48), " ", I48)) | F48: Cereja Negra e Praliné | H48: 120ml | I48: Frasco | J48: Óleo bifásico \ hidra. intensa \ perfuma | L48: 43.9
B49: Natura | C49: Tododia | D49: Oleo Corporal | E49: =TRIM(CONCATENATE(D49, " ", C49, " ", F49, " ", IF(G49>0, G49 & "x" & H49, H49), " ", I49)) | F49: Cereja e Avelã | H49: 120ml | I49: Frasco | J49: Óleo bifásico \ hidra. intensa \ perfuma | L49: 43.9
B50: Natura | C50: Tododia | D50: Oleo Corporal | E50: =TRIM(CONCATENATE(D50, " ", C50, " ", F50, " ", IF(G50>0, G50 & "x" & H50, H50), " ", I50)) | F50: Ameixa e Flor de Baunilha | H50: 120ml | I50: Frasco | J50: Óleo bifásico \ hidra. intensa \ perfuma | L50: 43.9
B51: Natura | C51: Tododia | D51: Oleo Corporal | E51: =TRIM(CONCATENATE(D51, " ", C51, " ", F51, " ", IF(G51>0, G51 & "x" & H51, H51), " ", I51)) | F51: Tâmara e Canela | H51: 120ml | I51: Frasco | J51: Óleo bifásico \ hidra. intensa \ perfuma | L51: 43.9
B52: Natura | C52: Tododia | D52: Concentrado Relaxante | E52: =TRIM(CONCATENATE(D52, " ", C52, " ", F52, " ", IF(G52>0, G52 & "x" & H52, H52), " ", I52)) | F52: Todonoite | H52: 800g | I52: Tubo | J52: Concentrado Relaxante \ perfuma \ essencia relaxante | L52: R$ 66, 90
B53: Natura | C53: Tododia | D53: Sabonete em barra puro vegetal | E53: =TRIM(CONCATENATE(D53, " ", C53, " ", F53, " ", IF(G53>0, G53 & "x" & H53, H53), " ", I53)) | F53: Acerola e Hibisco | G53: 5 | H53: 90g | I53: Caixa | J53: Puro vegetal \ Nutritivo | L53: 33.9
B54: Natura | C54: Tododia | D54: Sabonete em barra puro vegetal | E54: =TRIM(CONCATENATE(D54, " ", C54, " ", F54, " ", IF(G54>0, G54 & "x" & H54, H54), " ", I54)) | F54: Algodão | G54: 5 | H54: 90g | I54: Caixa | J54: Acalma \ Relaxa | L54: 33.9
A55: NATBRA-72147 | B55: Natura | C55: Tododia | D55: Sabonete em barra puro vegetal | E55: =TRIM(CONCATENATE(D55, " ", C55, " ", F55, " ", IF(G55>0, G55 & "x" & H55, H55), " ", I55)) | F55: Alecrim e Sálvia | G55: 5 | H55: 90g | I55: Caixa | J55: Puro vegetal \ Nutritivo | L55: 33.9
A56: NATBRA-100535 | B56: Natura | C56: Tododia | D56: Sabonete em barra puro vegetal | E56: =TRIM(CONCATENATE(D56, " ", C56, " ", F56, " ", IF(G56>0, G56 & "x" & H56, H56), " ", I56)) | F56: Ameixa e Flor de Baunilha | G56: 5 | H56: 90g | I56: Caixa | J56: Puro vegetal \ Nutritivo | L56: 33.9
A57: NATBRA-87512 | B57: Natura | C57: Tododia | D57: Sabonete em barra puro vegetal | E57: =TRIM(CONCATENATE(D57, " ", C57, " ", F57, " ", IF(G57>0, G57 & "x" & H57, H57), " ", I57)) | F57: Amora Vermelha e Jabuticaba | G57: 5 | H57: 90g | I57: Caixa | J57: Puro vegetal \ Nutritivo | L57: 33.9
B58: Natura | C58: Tododia | D58: Sabonete em barra puro vegetal | E58: =TRIM(CONCATENATE(D58, " ", C58, " ", F58, " ", IF(G58>0, G58 & "x" & H58, H58), " ", I58)) | F58: Avelã e Cassis | G58: 5 | H58: 90g | I58: Caixa | J58: Puro vegetal \ Nutritivo | L58: 33.9
B59: Natura | C59: Tododia | D59: Sabonete em barra puro vegetal | E59: =TRIM(CONCATENATE(D59, " ", C59, " ", F59, " ", IF(G59>0, G59 & "x" & H59, H59), " ", I59)) | F59: Capim Limao e Hortela | G59: 5 | H59: 90g | I59: Caixa | J59: Puro vegetal \ Nutritivo | L59: 33.9
B60: Natura | C60: Tododia | D60: Sabonete em barra puro vegetal | E60: =TRIM(CONCATENATE(D60, " ", C60, " ", F60, " ", IF(G60>0, G60 & "x" & H60, H60), " ", I60)) | F60: Cereja Negra e Pranilé | G60: 5 | H60: 90g | I60: Caixa | J60: Puro vegetal \ Nutritivo | L60: 33.9
A61: NATBRA-95840 | B61: Natura | C61: Tododia | D61: Sabonete em barra puro vegetal | E61: =TRIM(CONCATENATE(D61, " ", C61, " ", F61, " ", IF(G61>0, G61 & "x" & H61, H61), " ", I61)) | F61: Cereja e Avelã | G61: 5 | H61: 90g | I61: Caixa | J61: Acalma \ Relaxa \ nutritivo | L61: 33.9
B62: Natura | C62: Tododia | D62: Sabonete em barra puro vegetal | E62: =TRIM(CONCATENATE(D62, " ", C62, " ", F62, " ", IF(G62>0, G62 & "x" & H62, H62), " ", I62)) | F62: Todonoite | G62: 5 | H62: 90g | I62: Caixa | J62: energizante \ Nutritivo | L62: 33.9
B63: Natura | C63: Tododia | D63: Sabonete em barra puro vegetal | E63: =TRIM(CONCATENATE(D63, " ", C63, " ", F63, " ", IF(G63>0, G63 & "x" & H63, H63), " ", I63)) | F63: Energ. Flor de Gengibre e Tangerina | G63: 5 | H63: 90g | I63: Caixa | J63: Energizante \ Puro vegetal \ Nutritivo | L63: 33.9
B64: Natura | C64: Tododia | D64: Sabonete em barra puro vegetal | E64: =TRIM(CONCATENATE(D64, " ", C64, " ", F64, " ", IF(G64>0, G64 & "x" & H64, H64), " ", I64)) | F64: Framboesa e PImenta Rosa | G64: 5 | H64: 90g | I64: Caixa | J64: Puro vegetal \ Nutritivo | L64: 33.9
B65: Natura | C65: Tododia | D65: Sabonete em barra puro vegetal | E65: =TRIM(CONCATENATE(D65, " ", C65, " ", F65, " ", IF(G65>0, G65 & "x" & H65, H65), " ", I65)) | F65: Frutas Vermelha | G65: 5 | H65: 90g | I65: Caixa | J65: Puro vegetal \ Nutritivo | L65: 33.9
B66: Natura | C66: Tododia | D66: Sabonete em barra puro vegetal | E66: =TRIM(CONCATENATE(D66, " ", C66, " ", F66, " ", IF(G66>0, G66 & "x" & H66, H66), " ", I66)) | F66: Jasmim e Bergamota | G66: 5 | H66: 90g | I66: Caixa | J66: Puro vegetal \ Nutritivo | L66: 33.9
B67: Natura | C67: Tododia | D67: Sabonete em barra puro vegetal | E67: =TRIM(CONCATENATE(D67, " ", C67, " ", F67, " ", IF(G67>0, G67 & "x" & H67, H67), " ", I67)) | F67: Manga Rosa e Àgua de Coco | G67: 5 | H67: 90g | I67: Caixa | J67: Puro vegetal \ Nutritivo | L67: 33.9
B68: Natura | C68: Tododia | D68: Sabonete em barra puro vegetal | E68: =TRIM(CONCATENATE(D68, " ", C68, " ", F68, " ", IF(G68>0, G68 & "x" & H68, H68), " ", I68)) | F68: Maçã Caramelada e Baunilha | G68: 5 | H68: 90g | I68: Caixa | J68: Nutritivo \ Especial São João \ Inspirada na Maçã do Amor | L68: 33.9
A69: NATBRA-2829 | B69: Natura | C69: Tododia | D69: Sabonete em barra puro vegetal | E69: =TRIM(CONCATENATE(D69, " ", C69, " ", F69, " ", IF(G69>0, G69 & "x" & H69, H69), " ", I69)) | F69: Macadamia | G69: 5 | H69: 90g | I69: Caixa | J69: Puro vegetal \ Nutritivo | L69: 33.9
B70: Natura | C70: Tododia | D70: Sabonete em barra puro vegetal | E70: =TRIM(CONCATENATE(D70, " ", C70, " ", F70, " ", IF(G70>0, G70 & "x" & H70, H70), " ", I70)) | F70: Noz Pecã e Cacau | G70: 5 | H70: 90g | I70: Caixa | J70: Puro vegetal \ Nutritivo | L70: 33.9
B71: Natura | C71: Tododia | D71: Sabonete em barra puro vegetal | E71: =TRIM(CONCATENATE(D71, " ", C71, " ", F71, " ", IF(G71>0, G71 & "x" & H71, H71), " ", I71)) | F71: Roma e Salvia | G71: 5 | H71: 90g | I71: Caixa | J71: Puro vegetal \ Nutritivo | L71: 33.9
B72: Natura | C72: Tododia | D72: Sabonete em barra puro vegetal | E72: =TRIM(CONCATENATE(D72, " ", C72, " ", F72, " ", IF(G72>0, G72 & "x" & H72, H72), " ", I72)) | F72: Romã e Flor de Amora | G72: 5 | H72: 90g | I72: Caixa | J72: Puro vegetal \ Nutritivo | L72: 33.9
A73: NATBRA-7733 | B73: Natura | C73: Tododia | D73: Sabonete em barra puro vegetal | E73: =TRIM(CONCATENATE(D73, " ", C73, " ", F73, " ", IF(G73>0, G73 & "x" & H73, H73), " ", I73)) | F73: Tâmara e Canela | G73: 5 | H73: 90g | I73: Caixa | J73: Puro vegetal \ Nutritivo | L73: 33.9
B74: Natura | C74: Tododia | D74: Sabonete em barra puro vegetal | E74: =TRIM(CONCATENATE(D74, " ", C74, " ", F74, " ", IF(G74>0, G74 & "x" & H74, H74), " ", I74)) | F74: Roma e Uva Rosa, Alecrin e Salvia | G74: 5 | H74: 90g | I74: Caixa | J74: Puro vegetal \ Nutritivo | L74: 41.9
B75: Natura | C75: Tododia | D75: Sabonete em barra puro vegetal | E75: =TRIM(CONCATENATE(D75, " ", C75, " ", F75, " ", IF(G75>0, G75 & "x" & H75, H75), " ", I75)) | F75: Flor de Lis, Alecrim, Framboesa e Pimenta Vermelha, Macadamia, Frutas Vermelhas | G75: 5 | H75: 90g | I75: Caixa | J75: Puro vegetal \ Nutritivo | L75: 41.9
B76: Natura | C76: Tododia | D76: Sabonete em barra puro vegetal | E76: =TRIM(CONCATENATE(D76, " ", C76, " ", F76, " ", IF(G76>0, G76 & "x" & H76, H76), " ", I76)) | F76: Ameixa e flor de baunilha, Ameixa e Flor de Cereja eRroma e Flor de Amora | G76: 5 | H76: 90g | I76: Caixa | J76: Puro vegetal \ Nutritivo | L76: 41.9
B77: Natura | C77: Tododia | D77: Sabonete Liquido Intimo | E77: =TRIM(CONCATENATE(D77, " ", C77, " ", F77, " ", IF(G77>0, G77 & "x" & H77, H77), " ", I77)) | F77: Algodão, Suave, Conforto | H77: 200ml | I77: Frasco | J77: Suave \ Conforto | L77: 49.9
B78: Natura | C78: Tododia | D78: Sabonete Liquido Intimo | E78: =TRIM(CONCATENATE(D78, " ", C78, " ", F78, " ", IF(G78>0, G78 & "x" & H78, H78), " ", I78)) | F78: Cereja e Avelã | H78: 200ml | I78: Frasco | J78: Proteção \ Cuidado | L78: 49.9
B79: Natura | C79: Tododia | D79: Sabonete Liquido Intimo | E79: =TRIM(CONCATENATE(D79, " ", C79, " ", F79, " ", IF(G79>0, G79 & "x" & H79, H79), " ", I79)) | F79: Delicado e Frescor | H79: 200ml | I79: Frasco | J79: Delicado \ Frescor | L79: 49.9
B80: Natura | C80: Tododia | D80: Sabonete Liquido Corpo e Esfoliante | E80: =TRIM(CONCATENATE(D80, " ", C80, " ", F80, " ", IF(G80>0, G80 & "x" & H80, H80), " ", I80)) | F80: Limão e Hortelã | H80: 190g | I80: Frasco | J80: Esfoliante | L80: 49.9
B81: Natura | C81: Tododia | D81: Esfoliante em Creme Corporal | E81: =TRIM(CONCATENATE(D81, " ", C81, " ", F81, " ", IF(G81>0, G81 & "x" & H81, H81), " ", I81)) | F81: Macadâmia | H81: 200ml | I81: Frasco | J81: Esfoliante | L81: 49.9
B82: Natura | C82: Tododia | D82: Esfoliante em Creme Corporal | E82: =TRIM(CONCATENATE(D82, " ", C82, " ", F82, " ", IF(G82>0, G82 & "x" & H82, H82), " ", I82)) | F82: Jambo Rosa e Flor de Caju | H82: 190g | I82: Frasco | J82: Esfoliante Nutritivo \ Suaviza \ Perfuma | L82: 49.9
B83: Natura | C83: Tododia | D83: Geleia Desodorante Iluminador | E83: =TRIM(CONCATENATE(D83, " ", C83, " ", F83, " ", IF(G83>0, G83 & "x" & H83, H83), " ", I83)) | F83: Jambo Rosa e Flor de Caju | H83: 100g | I83: Frasco | J83: Gelia Iluminador \ Desosrante \ Perfuma | L83: R$ 59, 90
B84: Natura | C84: Tododia | D84: Agua pre-biotica para o corpo | E84: =TRIM(CONCATENATE(D84, " ", C84, " ", F84, " ", IF(G84>0, G84 & "x" & H84, H84), " ", I84)) | F84: Manga Rosa e Água de Coco | H84: 150ml | I84: Frasco | J84: Hidrata e Refresca a Pele | L84: R$ 60, 00
B85: Natura | C85: Tododia | D85: Bruma Facil | E85: =TRIM(CONCATENATE(D85, " ", C85, " ", F85, " ", IF(G85>0, G85 & "x" & H85, H85), " ", I85)) | F85: Flor de Gengibre e Tangerina | H85: 100ml | I85: Frasco | J85: Energizante \ spray Facil | L85: 49.9
B86: Natura | C86: Tododia | D86: Creme Desodorante | E86: =TRIM(CONCATENATE(D86, " ", C86, " ", F86, " ", IF(G86>0, G86 & "x" & H86, H86), " ", I86)) | F86: Flor de Gengibre e Tangerina | H86: 200ml | I86: Frasco | J86: 2 em 1 \ Energizante \ Nutritivo | L86: 51.9
A87: NATBRA-189404 | B87: Natura | C87: Tododia | D87: Desodorante Antitranspirante Roll-on | E87: =TRIM(CONCATENATE(D87, " ", C87, " ", F87, " ", IF(G87>0, G87 & "x" & H87, H87), " ", I87)) | F87: Aclarar | H87: 70ml | I87: Frasco | L87: 29.9
A88: NATBRA-189401 | B88: Natura | C88: Tododia | D88: Desodorante Antitranspirante Roll-on | E88: =TRIM(CONCATENATE(D88, " ", C88, " ", F88, " ", IF(G88>0, G88 & "x" & H88, H88), " ", I88)) | F88: Algodão | H88: 70ml | I88: Frasco | L88: 29.9
B89: Natura | C89: Tododia | D89: Desodorante Antitranspirante Roll-on | E89: =TRIM(CONCATENATE(D89, " ", C89, " ", F89, " ", IF(G89>0, G89 & "x" & H89, H89), " ", I89)) | F89: Alecrim e Salvia | H89: 70ml | I89: Frasco | J89: Proteção Inv \ 0% Alcool | L89: 29.9
B90: Natura | C90: Tododia | D90: Desodorante Antitranspirante Roll-on | E90: =TRIM(CONCATENATE(D90, " ", C90, " ", F90, " ", IF(G90>0, G90 & "x" & H90, H90), " ", I90)) | F90: Ameixa e Flor de Baunilha | H90: 70ml | I90: Frasco | J90: Proteção Performace\ Secagem Rapida | L90: 29.9
B91: Natura | C91: Tododia | D91: Desodorante Antitranspirante Roll-on | E91: =TRIM(CONCATENATE(D91, " ", C91, " ", F91, " ", IF(G91>0, G91 & "x" & H91, H91), " ", I91)) | F91: Amora Vermelha e Jabuticba | H91: 70ml | I91: Frasco | J91: Proteção Performace\ Secagem Rapida | L91: 29.9
B92: Natura | C92: Tododia | D92: Desodorante Antitranspirante Roll-on | E92: =TRIM(CONCATENATE(D92, " ", C92, " ", F92, " ", IF(G92>0, G92 & "x" & H92, H92), " ", I92)) | F92: Capim Limão e Hortelã | H92: 70ml | I92: Frasco | J92: Proteção Inv \ 0% Alcool | L92: 29.9
B93: Natura | C93: Tododia | D93: Desodorante Antitranspirante Roll-on | E93: =TRIM(CONCATENATE(D93, " ", C93, " ", F93, " ", IF(G93>0, G93 & "x" & H93, H93), " ", I93)) | F93: Cereja e Avelã | H93: 70ml | I93: Frasco | J93: Proteção Performace\ Secagem Rapida | L93: 29.9
A94: NATBRA-189402 | B94: Natura | C94: Tododia | D94: Desodorante Antitranspirante Roll-on | E94: =TRIM(CONCATENATE(D94, " ", C94, " ", F94, " ", IF(G94>0, G94 & "x" & H94, H94), " ", I94)) | F94: Macadania | H94: 70ml | I94: Frasco | J94: Proteção Performace\ Secagem Rapida | L94: 29.9
B95: Natura | C95: Tododia | D95: Desodorante Antitranspirante Roll-on | E95: =TRIM(CONCATENATE(D95, " ", C95, " ", F95, " ", IF(G95>0, G95 & "x" & H95, H95), " ", I95)) | F95: Tamara e Canela | H95: 70ml | I95: Frasco | J95: Proteção Performace\ Secagem Rapida | L95: 29.9
B96: Natura | C96: Tododia | D96: Desodorante Antitranspirante Roll-on | E96: =TRIM(CONCATENATE(D96, " ", C96, " ", F96, " ", IF(G96>0, G96 & "x" & H96, H96), " ", I96)) | F96: Sem Perfume | H96: 70ml | I96: Frasco | J96: Proteção Performace\ Secagem Rapida | L96: 29.9
A97: NATBRA-179542 | B97: Natura | C97: Tododia | D97: Desodorante Creme | E97: =TRIM(CONCATENATE(D97, " ", C97, " ", F97, " ", IF(G97>0, G97 & "x" & H97, H97), " ", I97)) | F97: Ameixa e Flor de Baunilha | H97: 80g | I97: Frasco | J97: Proteção Inv \ 0% Alcool \ Performace | L97: 30.9
B98: Natura | C98: Tododia | D98: Desodorante Creme | E98: =TRIM(CONCATENATE(D98, " ", C98, " ", F98, " ", IF(G98>0, G98 & "x" & H98, H98), " ", I98)) | F98: Cereja e Avela | H98: 80g | I98: Frasco | J98: Proteção Inv \ 0% Alcool \ Performace | L98: 30.9
B99: Natura | C99: Tododia | D99: Desodorante Creme | E99: =TRIM(CONCATENATE(D99, " ", C99, " ", F99, " ", IF(G99>0, G99 & "x" & H99, H99), " ", I99)) | F99: Invisível | H99: 80g | I99: Frasco | J99: Proteção Inv \ 0% Alcool \ Performace | L99: 30.9
B100: Natura | C100: Tododia | D100: Desodorante Creme | E100: =TRIM(CONCATENATE(D100, " ", C100, " ", F100, " ", IF(G100>0, G100 & "x" & H100, H100), " ", I100)) | F100: Leite de Algodao | H100: 80g | I100: Frasco | J100: Proteção Inv \ 0% Alcool \ Performace | L100: 30.9
B101: Natura | C101: Tododia | D101: Desodorante Creme | E101: =TRIM(CONCATENATE(D101, " ", C101, " ", F101, " ", IF(G101>0, G101 & "x" & H101, H101), " ", I101)) | F101: Macadâmia | H101: 80g | I101: Frasco | J101: Proteção Inv \ 0% Alcool \ Performace | L101: 30.9
B102: Natura | C102: Tododia | D102: Desodorante Creme | E102: =TRIM(CONCATENATE(D102, " ", C102, " ", F102, " ", IF(G102>0, G102 & "x" & H102, H102), " ", I102)) | F102: Manga Rosa e Aguá de Coco | H102: 80g | I102: Frasco | J102: Proteção Inv \ 0% Alcool \ Performace | L102: 30.9
B103: Natura | C103: Tododia | D103: Desodorante Creme | E103: =TRIM(CONCATENATE(D103, " ", C103, " ", F103, " ", IF(G103>0, G103 & "x" & H103, H103), " ", I103)) | F103: Noz Pecã e Cacau | H103: 80g | I103: Frasco | J103: Proteção Inv \ 0% Alcool \ Performace | L103: 30.9
B104: Natura | C104: Tododia | D104: Creme Para Maos e Pes | E104: =TRIM(CONCATENATE(D104, " ", C104, " ", F104, " ", IF(G104>0, G104 & "x" & H104, H104), " ", I104)) | F104: Algodão | H104: 50ml | I104: Frasco | J104: Nutritivo \ Prebiotico | L104: 36.9
B105: Natura | C105: Tododia | D105: Creme Para Maos e Pes | E105: =TRIM(CONCATENATE(D105, " ", C105, " ", F105, " ", IF(G105>0, G105 & "x" & H105, H105), " ", I105)) | F105: Ameixa e Flor de Baunilha | H105: 50ml | I105: Frasco | J105: Nutritivo \ Prebiotico | L105: 36.9
B106: Natura | C106: Tododia | D106: Creme Para Maos e Pes | E106: =TRIM(CONCATENATE(D106, " ", C106, " ", F106, " ", IF(G106>0, G106 & "x" & H106, H106), " ", I106)) | F106: Cereja e Avelã | H106: 50ml | I106: Frasco | J106: Nutritivo \ Prebiotico | L106: 36.9
B107: Natura | C107: Tododia | D107: Creme Para Maos e Pes | E107: =TRIM(CONCATENATE(D107, " ", C107, " ", F107, " ", IF(G107>0, G107 & "x" & H107, H107), " ", I107)) | F107: Noz Pecã e Cacau | H107: 50ml | I107: Frasco | J107: Sem desodorante | L107: 36.9
...

Sheet Movimento
A1: Data | B1: COD do Produto | C1: Produto | D1: Cliente | E1: Tipo de Movimentação | F1: Quantidade | G1: Preço Custo Total | H1: Preço Venda Total | I1: Observações | J1: Status | K1: Data Prevista | L1: Tipo de Pagamento | M1: ID_Venda
A2: 45992.599 | B2: NATBRA-2816 | C2: Natura Hidrante Desodorante Corporal Tododia Algodão 400ml Frasco | D2: NATURA | E2: ENTRADA | F2: 5 | G2: 320 | H2: 379.5 | I2: Ciclo 23 | J2: PAGO | K2: 45993 | L2: Pix | M2: E-27B7FB
A3: 45992.599 | B3: NATBRA-2816 | C3: Natura Hidrante Desodorante Corporal Tododia Algodão 400ml Frasco | D3: ASD | E3: SAÍDA | F3: -1 | G3: -64 | H3: 75.9 | J3: PAGO | K3: 2025-12-01 14:22:36 | L3: Pix | M3: V-C8C229
A4: 45993.599 | B4: NATBRA-190159 | C4: =VLOOKUP(B4,Produtos!$A:$E,5,FALSE) | D4: NATURA | E4: ENTRADA | F4: 1 | G4: 21.23 | H4: 0 | J4: PAGO | L4: Pix
A5: 45994.599 | B5: NATBRA-152290 | C5: =VLOOKUP(B5,Produtos!$A:$E,5,FALSE) | D5: NATURA | E5: ENTRADA | F5: 1 | G5: 21.23 | H5: 0 | J5: PAGO | L5: Pix
A6: 45995.599 | B6: NATBRA-116779 | C6: =VLOOKUP(B6,Produtos!$A:$E,5,FALSE) | D6: NATURA | E6: ENTRADA | F6: 3 | G6: 91.76 | H6: 0 | J6: PAGO | L6: Pix
A7: 45996.599 | B7: NATBRA-959847 | C7: =VLOOKUP(B7,Produtos!$A:$E,5,FALSE) | D7: NATURA | E7: ENTRADA | F7: 3 | G7: 236.06 | H7: 0 | J7: PAGO | L7: Pix
A8: 45997.599 | B8: NATBRA-112866 | C8: =VLOOKUP(B8,Produtos!$A:$E,5,FALSE) | D8: NATURA | E8: ENTRADA | F8: 3 | G8: 36.95 | H8: 0 | J8: PAGO | L8: Pix
A9: 45998.599 | B9: NATBRA-159951 | C9: =VLOOKUP(B9,Produtos!$A:$E,5,FALSE) | D9: NATURA | E9: ENTRADA | F9: 3 | G9: 59.95 | H9: 0 | J9: PAGO | L9: Pix
A10: 45999.599 | B10: NATBRA-782675 | C10: =VLOOKUP(B10,Produtos!$A:$E,5,FALSE) | D10: NATURA | E10: ENTRADA | F10: 3 | G10: 177.13 | H10: 0 | J10: PAGO | L10: Pix
A11: 46000.599 | B11: NATBRA-817061 | C11: =VLOOKUP(B11,Produtos!$A:$E,5,FALSE) | D11: NATURA | E11: ENTRADA | F11: 3 | G11: 204.52 | H11: 0 | J11: PAGO | L11: Pix
A12: 46001.599 | B12: NATBRA-817060 | C12: =VLOOKUP(B12,Produtos!$A:$E,5,FALSE) | D12: NATURA | E12: ENTRADA | F12: 3 | G12: 56.37 | H12: 0 | J12: PAGO | L12: Pix
A13: 46003.599 | B13: NATBRA-149374 | C13: =VLOOKUP(B13,Produtos!$A:$E,5,FALSE) | D13: NATURA | E13: ENTRADA | F13: 3 | G13: 38.95 | H13: 0 | J13: PAGO | L13: Pix
A14: 46005.599 | B14: NATBRA-151033 | C14: =VLOOKUP(B14,Produtos!$A:$E,5,FALSE) | D14: NATURA | E14: ENTRADA | F14: 2 | G14: 31.25 | H14: 0 | J14: PAGO | L14: Pix
A15: 46006.599 | B15: NATBRA-9467 | C15: =VLOOKUP(B15,Produtos!$A:$E,5,FALSE) | D15: NATURA | E15: ENTRADA | F15: 2 | G15: 194.34 | H15: 0 | J15: PAGO | L15: Pix
... A56: 46052.599 | B56: NATBRA-56747 | C56: =VLOOKUP(B56,Produtos!$A:$E,5,FALSE) | D56: NATURA | E56: ENTRADA | F56: 3 | G56: 49.34 | H56: 0 | J56: PAGO | L56: Pix

Sheet Clientes
A1: ID_Cliente | B1: Nome | C1: Telefone | D1: Email | E1: Endereço | F1: Observações
A2: C-C2BFEE | B2: Joana | C2: 11 92393287 | D2: dsadsa@gmail.com | E2: Cachoeira | F2: Loja Whats
A3: C-4C4B74 | B3: ASDDAS | C3: 2232 | D3: sadlapsd@gmail.com | E3: Furnas | F3: Site
A4: C-0947A0 | B4: FGGH | C4: asdasd | D4: asdasd | E4: asd | F4: dasda
A5: C-7482A8 | B5: GHHHH | F5: Cadastrado via Venda

Sheet Relatorio
A1: FATURAMENTO BRUTO | B1: =SUMIFS(Movimento!H:H, Movimento!E:E, "SAÍDA", Movimento!J:J, "PAGO")
A2: CUSTO DE MERCADORIA VENDIDA (CMV) | B2: =SUMIFS(Movimento!G:G, Movimento!E:E, "SAÍDA") * -1
A3: LUCRO BRUTO TOTAL | B3: =B1 - B2
A4: MARGEM BRUTA (%) | B4: =(B3 / B1)
A5: QTD PRODUTOS FIADO | B5: =SUMIFS(Movimento!F:F, Movimento!J:J, "A RECEBER") * -1
A6: VALOR A RECEBER (FIADO) | B6: =SUMIFS(Movimento!H:H, Movimento!J:J, "A RECEBER")
A7: ESTOQUE TOTAL (ITENS) | B7: =SUM(Movimento!F:F)
A8: CUSTO TOTAL DO ESTOQUE ATUAL | B8: =SUM(Movimento!G:G)
A9: SALDO DE CAIXA DO ESTOQUE | B9: =B1- B8
