Workbook

Sheet Produtos
A1: COD | B1: Marca | C1: Coleção | D1: Categoria | E1: Produto | F1: Nome | G1: Unidade | H1: Volume | I1: Tipo | J1: Descrição | K1: Preço Custo | L1: Preço Venda | M1: Estoque | N1: Status estoque
B2: Natura | C2: Tododia | D2: Hidrante Desodorante Corporal | E2: =TRIM(CONCATENATE(C2, " ", D2, " ", F2, " ", IF(G2>0, G2 & "x" & H2, H2), " ", I2)) -> Tododia Hidrante Desodorante Corporal Algodão 400ml Frasco | F2: Algodão | H2: 400ml | I2: Frasco | J2: Desodorante / nutritivo / creme | K2: 76 | L2: 76 | M2: =SUMIF(Movimento!B:B, A2, Movimento!F:F) -> 0 | N2: =IF(M2=0,"Falta Pedir!",IF(M2<=3,"Baixo Estoque","Em Estoque")) -> Falta Pedir!
B3: Natura | C3: Tododia | D3: Hidrante Desodorante Corporal | E3: =TRIM(CONCATENATE(C3, " ", D3, " ", F3, " ", IF(G3>0, G3 & "x" & H3, H3), " ", I3)) -> Tododia Hidrante Desodorante Corporal Ameixa e Flor de Baunilha 400ml Frasco | F3: Ameixa e Flor de Baunilha | H3: 400ml | I3: Frasco | J3: Suave de Algodão \ Nutritivo | K3: 75.9 | L3: 75.9 | M3: =SUMIF(Movimento!B:B, A3, Movimento!F:F) -> 0 | N3: =IF(M3=0,"Falta Pedir!",IF(M3<=3,"Baixo Estoque","Em Estoque")) -> Falta Pedir!
B4: Natura | C4: Tododia | D4: Hidrante Desodorante Corporal | E4: =TRIM(CONCATENATE(C4, " ", D4, " ", F4, " ", IF(G4>0, G4 & "x" & H4, H4), " ", I4)) -> Tododia Hidrante Desodorante Corporal Acerola e Hibisco 400ml Frasco | F4: Acerola e Hibisco | H4: 400ml | I4: Frasco | J4: Refrescante / Gelado | K4: 75.9 | L4: 75.9
B5: Natura | C5: Tododia | D5: Hidrante Desodorante Corporal | E5: =TRIM(CONCATENATE(C5, " ", D5, " ", F5, " ", IF(G5>0, G5 & "x" & H5, H5), " ", I5)) -> Tododia Hidrante Desodorante Corporal Amora Vermelha e Jabuticaba 400ml Frasco | F5: Amora Vermelha e Jabuticaba | H5: 400ml | I5: Frasco | J5: Desodorante / nutritivo / creme | K5: 75.9 | L5: 75.9
B6: Natura | C6: Tododia | D6: Hidrante Desodorante Corporal | E6: =TRIM(CONCATENATE(C6, " ", D6, " ", F6, " ", IF(G6>0, G6 & "x" & H6, H6), " ", I6)) -> Tododia Hidrante Desodorante Corporal Capim Limão e Hortelã 400ml Frasco | F6: Capim Limão e Hortelã | H6: 400ml | I6: Frasco | J6: Desodorante / nutritivo / creme | K6: 75.9 | L6: 75.9
B7: Natura | C7: Tododia | D7: Hidrante Desodorante Corporal | E7: =TRIM(CONCATENATE(C7, " ", D7, " ", F7, " ", IF(G7>0, G7 & "x" & H7, H7), " ", I7)) -> Tododia Hidrante Desodorante Corporal Cereja Negra e Praliné 400ml Frasco | F7: Cereja Negra e Praliné | H7: 400ml | I7: Frasco | J7: Desodorante / nutritivo / creme | K7: 75.9 | L7: 75.9
B8: Natura | C8: Tododia | D8: Hidrante Desodorante Corporal | E8: =TRIM(CONCATENATE(C8, " ", D8, " ", F8, " ", IF(G8>0, G8 & "x" & H8, H8), " ", I8)) -> Tododia Hidrante Desodorante Corporal Cereja e Avela 400ml Frasco | F8: Cereja e Avela | H8: 400ml | I8: Frasco | J8: Desodorante / nutritivo / creme | K8: 75.9 | L8: 75.9
B9: Natura | C9: Tododia | D9: Hidrante Desodorante Corporal | E9: =TRIM(CONCATENATE(C9, " ", D9, " ", F9, " ", IF(G9>0, G9 & "x" & H9, H9), " ", I9)) -> Tododia Hidrante Desodorante Corporal Chá de Camomila e Lavanda 400ml Frasco | F9: Chá de Camomila e Lavanda | H9: 400ml | I9: Frasco | J9: HIdrata. Noturno \ calmante | K9: 75.9 | L9: 75.9
B10: Natura | C10: Tododia | D10: Hidrante Desodorante Corporal | E10: =TRIM(CONCATENATE(C10, " ", D10, " ", F10, " ", IF(G10>0, G10 & "x" & H10, H10), " ", I10)) -> Tododia Hidrante Desodorante Corporal Chá de Camomila e Lavanda 200ml Frasco | F10: Chá de Camomila e Lavanda | H10: 200ml | I10: Frasco | J10: HIdrata. Noturno \ calmante
B11: Natura | C11: Tododia | D11: Hidrante Desodorante Corporal | E11: =TRIM(CONCATENATE(C11, " ", D11, " ", F11, " ", IF(G11>0, G11 & "x" & H11, H11), " ", I11)) -> Tododia Hidrante Desodorante Corporal Flor de Gengibre e Tangerina 400 ml Frasco | F11: Flor de Gengibre e Tangerina | H11: 400 ml | I11: Frasco | J11: Nutritivo Energizante | K11: 75.9 | L11: 75.9
B12: Natura | C12: Tododia | D12: Hidrante Desodorante Corporal | E12: =TRIM(CONCATENATE(C12, " ", D12, " ", F12, " ", IF(G12>0, G12 & "x" & H12, H12), " ", I12)) -> Tododia Hidrante Desodorante Corporal Flor de Pera e Melissa 400ml Frasco | F12: Flor de Pera e Melissa | H12: 400ml | I12: Frasco | J12: Desodorante / nutritivo / creme | K12: 75.9 | L12: 75.9
B13: Natura | C13: Tododia | D13: Hidrante Desodorante Corporal | E13: =TRIM(CONCATENATE(C13, " ", D13, " ", F13, " ", IF(G13>0, G13 & "x" & H13, H13), " ", I13)) -> Tododia Hidrante Desodorante Corporal Framboesa e PImenta Vermelha 400ml Frasco | F13: Framboesa e PImenta Vermelha | H13: 400ml | I13: Frasco | J13: Desodorante / nutritivo / creme | K13: 75.9 | L13: 75.9
B14: Natura | C14: Tododia | D14: Hidrante Desodorante Corporal | E14: =TRIM(CONCATENATE(C14, " ", D14, " ", F14, " ", IF(G14>0, G14 & "x" & H14, H14), " ", I14)) -> Tododia Hidrante Desodorante Corporal Jambo Rosa e Flor De Caju 400ml Frasco | F14: Jambo Rosa e Flor De Caju | H14: 400ml | I14: Frasco | J14: Desodorante / nutritivo / creme | K14: 75.9 | L14: 75.9
B15: Natura | C15: Tododia | D15: Hidrante Desodorante Corporal | E15: =TRIM(CONCATENATE(C15, " ", D15, " ", F15, " ", IF(G15>0, G15 & "x" & H15, H15), " ", I15)) -> Tododia Hidrante Desodorante Corporal Limão Siciliano e Flor de Gardênia 400ml Frasco | F15: Limão Siciliano e Flor de Gardênia | H15: 400ml | I15: Frasco | J15: Desodorante / nutritivo / creme | K15: 75.9 | L15: 75.9
B16: Natura | C16: Tododia | D16: Hidrante Desodorante Corporal | E16: =TRIM(CONCATENATE(C16, " ", D16, " ", F16, " ", IF(G16>0, G16 & "x" & H16, H16), " ", I16)) -> Tododia Hidrante Desodorante Corporal Macadâmia 400ml Frasco | F16: Macadâmia | H16: 400ml | I16: Frasco | J16: Desodorante / nutritivo / creme | K16: 75.9 | L16: 75.9
B17: Natura | C17: Tododia | D17: Hidrante Desodorante Corporal | E17: =TRIM(CONCATENATE(C17, " ", D17, " ", F17, " ", IF(G17>0, G17 & "x" & H17, H17), " ", I17)) -> Tododia Hidrante Desodorante Corporal Maça Caramelada e Baunilha 400ml Frasco | F17: Maça Caramelada e Baunilha | H17: 400ml | I17: Frasco | J17: Nutritivo \ Especial São João \ Inspirada na Maçã do Amor | K17: 75.9 | L17: 75.9
B18: Natura | C18: Tododia | D18: Hidrante Desodorante Corporal | E18: =TRIM(CONCATENATE(C18, " ", D18, " ", F18, " ", IF(G18>0, G18 & "x" & H18, H18), " ", I18)) -> Tododia Hidrante Desodorante Corporal Manga Rosa e Àgua de Coco 400ml Frasco | F18: Manga Rosa e Àgua de Coco | H18: 400ml | I18: Frasco | J18: Refrescante / Gelado | K18: 75.9 | L18: 75.9
B19: Natura | C19: Tododia | D19: Hidrante Desodorante Corporal | E19: =TRIM(CONCATENATE(C19, " ", D19, " ", F19, " ", IF(G19>0, G19 & "x" & H19, H19), " ", I19)) -> Tododia Hidrante Desodorante Corporal Nóz Pecão e Cacau 400ml Frasco | F19: Nóz Pecão e Cacau | H19: 400ml | I19: Frasco | J19: Desodorante / nutritivo / creme | K19: 75.9 | L19: 75.9
B20: Natura | C20: Tododia | D20: Hidrante Desodorante Corporal | E20: =TRIM(CONCATENATE(C20, " ", D20, " ", F20, " ", IF(G20>0, G20 & "x" & H20, H20), " ", I20)) -> Tododia Hidrante Desodorante Corporal Roma e Salvia 400ml Frasco | F20: Roma e Salvia | H20: 400ml | I20: Frasco | J20: Desodorante / nutritivo / creme | K20: 75.9 | L20: 75.9
B21: Natura | C21: Tododia | D21: Hidrante Desodorante Corporal | E21: =TRIM(CONCATENATE(C21, " ", D21, " ", F21, " ", IF(G21>0, G21 & "x" & H21, H21), " ", I21)) -> Tododia Hidrante Desodorante Corporal Romã e Flor de Amora 400ml Frasco | F21: Romã e Flor de Amora | H21: 400ml | I21: Frasco | J21: Desodorante / nutritivo / creme | K21: 75.9 | L21: 75.9
B22: Natura | C22: Tododia | D22: Hidrante Desodorante Corporal | E22: =TRIM(CONCATENATE(C22, " ", D22, " ", F22, " ", IF(G22>0, G22 & "x" & H22, H22), " ", I22)) -> Tododia Hidrante Desodorante Corporal Tâmara e Canela 400ml Frasco | F22: Tâmara e Canela | H22: 400ml | I22: Frasco | J22: Desodorante / nutritivo / creme | K22: 75.9 | L22: 75.9
... B30: Natura | C30: Tododia | D30: Hidrante Desodorante Corporal | E30: =TRIM(CONCATENATE(C30, " ", D30, " ", F30, " ", IF(G30>0, G30 & "x" & H30, H30), " ", I30)) -> Tododia Hidrante Desodorante Corporal Chá de Camomila e Lavanda 400ml Refil | F30: Chá de Camomila e Lavanda | H30: 400ml | I30: Refil | J30: Hidrata. Noturno \ calmante | K30: 56.4 | L30: 56.4
B31: Natura | C31: Tododia | D31: Hidrante Desodorante Corporal | E31: =TRIM(CONCATENATE(C31, " ", D31, " ", F31, " ", IF(G31>0, G31 & "x" & H31, H31), " ", I31)) -> Tododia Hidrante Desodorante Corporal Chá de Camomila e Lavanda 200ml Refil | F31: Chá de Camomila e Lavanda | H31: 200ml | I31: Refil | J31: Hidrata. Noturno \ calmante
B32: Natura | C32: Tododia | D32: Hidrante Desodorante Corporal | E32: =TRIM(CONCATENATE(C32, " ", D32, " ", F32, " ", IF(G32>0, G32 & "x" & H32, H32), " ", I32)) -> Tododia Hidrante Desodorante Corporal Flor de Gengibre e Tangerina 400ml Refil | F32: Flor de Gengibre e Tangerina | H32: 400ml | I32: Refil | J32: Hidrata. Noturno \ calmante | K32: 56.4 | L32: 56.4
B33: Natura | C33: Tododia | D33: Hidrante Desodorante Corporal | E33: =TRIM(CONCATENATE(C33, " ", D33, " ", F33, " ", IF(G33>0, G33 & "x" & H33, H33), " ", I33)) -> Tododia Hidrante Desodorante Corporal Flor de Pera e Melissa 400ml Refil | F33: Flor de Pera e Melissa | H33: 400ml | I33: Refil | J33: Desodorante / nutritivo / creme | K33: 56.4 | L33: 56.4
B34: Natura | C34: Tododia | D34: Hidrante Desodorante Corporal | E34: =TRIM(CONCATENATE(C34, " ", D34, " ", F34, " ", IF(G34>0, G34 & "x" & H34, H34), " ", I34)) -> Tododia Hidrante Desodorante Corporal Framboesa e PImenta Vermelha 400ml Refil | F34: Framboesa e PImenta Vermelha | H34: 400ml | I34: Refil | J34: Desodorante / nutritivo / creme | K34: 56.4 | L34: 56.4
B35: Natura | C35: Tododia | D35: Hidrante Desodorante Corporal | E35: =TRIM(CONCATENATE(C35, " ", D35, " ", F35, " ", IF(G35>0, G35 & "x" & H35, H35), " ", I35)) -> Tododia Hidrante Desodorante Corporal Jambo Rosa e Flor De Caju 400ml Refil | F35: Jambo Rosa e Flor De Caju | H35: 400ml | I35: Refil | J35: Desodorante / nutritivo / creme | K35: 56.4 | L35: 56.4
B36: Natura | C36: Tododia | D36: Hidrante Desodorante Corporal | E36: =TRIM(CONCATENATE(C36, " ", D36, " ", F36, " ", IF(G36>0, G36 & "x" & H36, H36), " ", I36)) -> Tododia Hidrante Desodorante Corporal Limão Siciliano e Flor de Gardênia 400ml Refil | F36: Limão Siciliano e Flor de Gardênia | H36: 400ml | I36: Refil | J36: Nutritivo Energizante | K36: 56.4 | L36: 56.4
B37: Natura | C37: Tododia | D37: Hidrante Desodorante Corporal | E37: =TRIM(CONCATENATE(C37, " ", D37, " ", F37, " ", IF(G37>0, G37 & "x" & H37, H37), " ", I37)) -> Tododia Hidrante Desodorante Corporal Macadâmia 400ml Refil | F37: Macadâmia | H37: 400ml | I37: Refil | J37: Desodorante / nutritivo / creme | K37: 56.4 | L37: 56.4
B38: Natura | C38: Tododia | D38: Hidrante Desodorante Corporal | E38: =TRIM(CONCATENATE(C38, " ", D38, " ", F38, " ", IF(G38>0, G38 & "x" & H38, H38), " ", I38)) -> Tododia Hidrante Desodorante Corporal Maça Caramelada e Baunilha 400ml Refil | F38: Maça Caramelada e Baunilha | H38: 400ml | I38: Refil | J38: Nutritivo \ Especial São João \ Inspirada na Maçã do Amor | K38: 56.4 | L38: 56.4
B39: Natura | C39: Tododia | D39: Hidrante Desodorante Corporal | E39: =TRIM(CONCATENATE(C39, " ", D39, " ", F39, " ", IF(G39>0, G39 & "x" & H39, H39), " ", I39)) -> Tododia Hidrante Desodorante Corporal Manga Rosa e Àgua de Coco 400ml Refil | F39: Manga Rosa e Àgua de Coco | H39: 400ml | I39: Refil | J39: Refrescante / Gelado | K39: 56.4 | L39: 56.4
B40: Natura | C40: Tododia | D40: Hidrante Desodorante Corporal | E40: =TRIM(CONCATENATE(C40, " ", D40, " ", F40, " ", IF(G40>0, G40 & "x" & H40, H40), " ", I40)) -> Tododia Hidrante Desodorante Corporal Nóz Pecão e Cacau 400ml Refil | F40: Nóz Pecão e Cacau | H40: 400ml | I40: Refil | J40: Desodorante / nutritivo / creme | K40: 56.4 | L40: 56.4
B41: Natura | C41: Tododia | D41: Hidrante Desodorante Corporal | E41: =TRIM(CONCATENATE(C41, " ", D41, " ", F41, " ", IF(G41>0, G41 & "x" & H41, H41), " ", I41)) -> Tododia Hidrante Desodorante Corporal Romã e Flor de Amora 400ml Refil | F41: Romã e Flor de Amora | H41: 400ml | I41: Refil | J41: Desodorante / nutritivo / creme | K41: 56.4 | L41: 56.4
B42: Natura | C42: Tododia | D42: Hidrante Desodorante Corporal | E42: =TRIM(CONCATENATE(C42, " ", D42, " ", F42, " ", IF(G42>0, G42 & "x" & H42, H42), " ", I42)) -> Tododia Hidrante Desodorante Corporal Tâmara e Canela 400ml Refil | F42: Tâmara e Canela | H42: 400ml | I42: Refil | J42: Desodorante / nutritivo / creme | K42: 56.4 | L42: 56.4
B43: Natura | C43: Tododia | D43: Creme Hidratante | E43: =TRIM(CONCATENATE(C43, " ", D43, " ", F43, " ", IF(G43>0, G43 & "x" & H43, H43), " ", I43)) -> Tododia Creme Hidratante Chá de Camomila e Lavanda 200ml Pote | F43: Chá de Camomila e Lavanda | H43: 200ml | I43: Pote | J43: Creme Hidrat. Prebiotica \ Vitam +B5 \ Para Massagem | K43: 81.9 | L43: 81.9
B44: Natura | C44: Tododia | D44: Creme Hidratante | E44: =TRIM(CONCATENATE(C44, " ", D44, " ", F44, " ", IF(G44>0, G44 & "x" & H44, H44), " ", I44)) -> Tododia Creme Hidratante Cereja e Avelã 200ml Pote | F44: Cereja e Avelã | H44: 200ml | I44: Pote | J44: Creme Amanteigado \ Perfumado \ Desodorante
B45: Natura | C45: Tododia | D45: Creme Hidratante | E45: =TRIM(CONCATENATE(C45, " ", D45, " ", F45, " ", IF(G45>0, G45 & "x" & H45, H45), " ", I45)) -> Tododia Creme Hidratante Cereja Negra e Praliné 250g Pote | F45: Cereja Negra e Praliné | H45: 250g | I45: Pote | J45: Pele Macia \\ Como Veludo \\ HIdrata. e PErfuma 2x Mais | K45: 81.9 | L45: 81.9
B46: Natura | C46: Tododia | D46: Manteiga Creme Corporal | E46: =TRIM(CONCATENATE(C46, " ", D46, " ", F46, " ", IF(G46>0, G46 & "x" & H46, H46), " ", I46)) -> Tododia Manteiga Creme Corporal Jambo Rosa e Flor De Caju 200g Pote | F46: Jambo Rosa e Flor De Caju | H46: 200g | I46: Pote | J46: Hidratante / Manteiga para o corpo hidrata \ Uniformiza \ Desodorante | K46: 81.9 | L46: 81.9
B47: Natura | C47: Tododia | D47: Oleo Creme Corporal | E47: =TRIM(CONCATENATE(C47, " ", D47, " ", F47, " ", IF(G47>0, G47 & "x" & H47, H47), " ", I47)) -> Tododia Oleo Creme Corporal Jambo Rosa e Flor De Caju 200ml Pote | F47: Jambo Rosa e Flor De Caju | H47: 200ml | I47: Pote | J47: Ultranutritivo \ Restaurador \ Desodorante | K47: 81.9 | L47: 81.9
B48: Natura | C48: Tododia | D48: Oleo Corporal | E48: =TRIM(CONCATENATE(C48, " ", D48, " ", F48, " ", IF(G48>0, G48 & "x" & H48, H48), " ", I48)) -> Tododia Oleo Corporal Cereja Negra e Praliné 120ml Frasco | F48: Cereja Negra e Praliné | H48: 120ml | I48: Frasco | J48: Óleo bifásico \ hidra. intensa \ perfuma | K48: 43.9 | L48: 43.9
B49: Natura | C49: Tododia | D49: Oleo Corporal | E49: =TRIM(CONCATENATE(C49, " ", D49, " ", F49, " ", IF(G49>0, G49 & "x" & H49, H49), " ", I49)) -> Tododia Oleo Corporal Cereja e Avelã 120ml Frasco | F49: Cereja e Avelã | H49: 120ml | I49: Frasco | J49: Óleo bifásico \ hidra. intensa \ perfuma | K49: 43.9 | L49: 43.9
B50: Natura | C50: Tododia | D50: Oleo Corporal | E50: =TRIM(CONCATENATE(C50, " ", D50, " ", F50, " ", IF(G50>0, G50 & "x" & H50, H50), " ", I50)) -> Tododia Oleo Corporal Ameixa e Flor de Baunilha 120ml Frasco | F50: Ameixa e Flor de Baunilha | H50: 120ml | I50: Frasco | J50: Óleo bifásico \ hidra. intensa \ perfuma | K50: 43.9 | L50: 43.9
B51: Natura | C51: Tododia | D51: Oleo Corporal | E51: =TRIM(CONCATENATE(C51, " ", D51, " ", F51, " ", IF(G51>0, G51 & "x" & H51, H51), " ", I51)) -> Tododia Oleo Corporal Tâmara e Canela 120ml Frasco | F51: Tâmara e Canela | H51: 120ml | I51: Frasco | J51: Óleo bifásico \ hidra. intensa \ perfuma | K51: 43.9 | L51: 43.9
B52: Natura | C52: Tododia | D52: Concentrado Relaxante | E52: =TRIM(CONCATENATE(C52, " ", D52, " ", F52, " ", IF(G52>0, G52 & "x" & H52, H52), " ", I52)) -> Tododia Concentrado Relaxante Chá de Camomila e Lavanda 800g Tubo | F52: Chá de Camomila e Lavanda | H52: 800g | I52: Tubo | J52: Concentrado Relaxante \ perfuma \ essencia relaxante | K52: R$ 66, 90 | L52: R$ 66, 90
B53: Natura | C53: Tododia | D53: Sabonete em barra puro vegetal | E53: =TRIM(CONCATENATE(C53, " ", D53, " ", F53, " ", IF(G53>0, G53 & "x" & H53, H53), " ", I53)) -> Tododia Sabonete em barra puro vegetal Acerola e Hibisco 5x90g Caixa | F53: Acerola e Hibisco | G53: 5 | H53: 90g | I53: Caixa | J53: Puro vegetal \ Nutritivo | K53: 33.9 | L53: 33.9
B54: Natura | C54: Tododia | D54: Sabonete em barra puro vegetal | E54: =TRIM(CONCATENATE(C54, " ", D54, " ", F54, " ", IF(G54>0, G54 & "x" & H54, H54), " ", I54)) -> Tododia Sabonete em barra puro vegetal Algodão 5x90g Caixa | F54: Algodão | G54: 5 | H54: 90g | I54: Caixa | J54: Acalma \ Relaxa | K54: 33.9 | L54: 33.9
B55: Natura | C55: Tododia | D55: Sabonete em barra puro vegetal | E55: =TRIM(CONCATENATE(C55, " ", D55, " ", F55, " ", IF(G55>0, G55 & "x" & H55, H55), " ", I55)) -> Tododia Sabonete em barra puro vegetal Alecrim e Sálvia 5x90g Caixa | F55: Alecrim e Sálvia | G55: 5 | H55: 90g | I55: Caixa | J55: Puro vegetal \ Nutritivo | K55: 33.9 | L55: 33.9
B56: Natura | C56: Tododia | D56: Sabonete em barra puro vegetal | E56: =TRIM(CONCATENATE(C56, " ", D56, " ", F56, " ", IF(G56>0, G56 & "x" & H56, H56), " ", I56)) -> Tododia Sabonete em barra puro vegetal Ameixa e Flor de Baunilha 5x90g Caixa | F56: Ameixa e Flor de Baunilha | G56: 5 | H56: 90g | I56: Caixa | J56: Puro vegetal \ Nutritivo | K56: 33.9 | L56: 33.9
B57: Natura | C57: Tododia | D57: Sabonete em barra puro vegetal | E57: =TRIM(CONCATENATE(C57, " ", D57, " ", F57, " ", IF(G57>0, G57 & "x" & H57, H57), " ", I57)) -> Tododia Sabonete em barra puro vegetal Amora Vermelha e Jabuticaba 5x90g Caixa | F57: Amora Vermelha e Jabuticaba | G57: 5 | H57: 90g | I57: Caixa | J57: Puro vegetal \ Nutritivo | K57: 33.9 | L57: 33.9
B58: Natura | C58: Tododia | D58: Sabonete em barra puro vegetal | E58: =TRIM(CONCATENATE(C58, " ", D58, " ", F58, " ", IF(G58>0, G58 & "x" & H58, H58), " ", I58)) -> Tododia Sabonete em barra puro vegetal Avelã e Cassis 5x90g Caixa | F58: Avelã e Cassis | G58: 5 | H58: 90g | I58: Caixa | J58: Puro vegetal \ Nutritivo | K58: 33.9 | L58: 33.9
B59: Natura | C59: Tododia | D59: Sabonete em barra puro vegetal | E59: =TRIM(CONCATENATE(C59, " ", D59, " ", F59, " ", IF(G59>0, G59 & "x" & H59, H59), " ", I59)) -> Tododia Sabonete em barra puro vegetal Capim Limao e Hortela 5x90g Caixa | F59: Capim Limao e Hortela | G59: 5 | H59: 90g | I59: Caixa | J59: Puro vegetal \ Nutritivo | K59: 33.9 | L59: 33.9
B60: Natura | C60: Tododia | D60: Sabonete em barra puro vegetal | E60: =TRIM(CONCATENATE(C60, " ", D60, " ", F60, " ", IF(G60>0, G60 & "x" & H60, H60), " ", I60)) -> Tododia Sabonete em barra puro vegetal Cereja Negra e Pranilé 5x90g Caixa | F60: Cereja Negra e Pranilé | G60: 5 | H60: 90g | I60: Caixa | J60: Puro vegetal \ Nutritivo | K60: 33.9 | L60: 33.9
B61: Natura | C61: Tododia | D61: Sabonete em barra puro vegetal | E61: =TRIM(CONCATENATE(C61, " ", D61, " ", F61, " ", IF(G61>0, G61 & "x" & H61, H61), " ", I61)) -> Tododia Sabonete em barra puro vegetal Cereja e Avelã 5x90g Caixa | F61: Cereja e Avelã | G61: 5 | H61: 90g | I61: Caixa | J61: Acalma \ Relaxa \ nutritivo | K61: 33.9 | L61: 33.9
B62: Natura | C62: Tododia | D62: Sabonete em barra puro vegetal | E62: =TRIM(CONCATENATE(C62, " ", D62, " ", F62, " ", IF(G62>0, G62 & "x" & H62, H62), " ", I62)) -> Tododia Sabonete em barra puro vegetal Chá de Camomila e Lavanda 5x90g Caixa | F62: Chá de Camomila e Lavanda | G62: 5 | H62: 90g | I62: Caixa | J62: energizante \ Nutritivo | K62: 33.9 | L62: 33.9
B63: Natura | C63: Tododia | D63: Sabonete em barra puro vegetal | E63: =TRIM(CONCATENATE(C63, " ", D63, " ", F63, " ", IF(G63>0, G63 & "x" & H63, H63), " ", I63)) -> Tododia Sabonete em barra puro vegetal Energ. Flor de Gengibre e Tangerina 5x90g Caixa | F63: Energ. Flor de Gengibre e Tangerina | G63: 5 | H63: 90g | I63: Caixa | J63: Energizante \ Puro vegetal \ Nutritivo | K63: 33.9 | L63: 33.9
B64: Natura | C64: Tododia | D64: Sabonete em barra puro vegetal | E64: =TRIM(CONCATENATE(C64, " ", D64, " ", F64, " ", IF(G64>0, G64 & "x" & H64, H64), " ", I64)) -> Tododia Sabonete em barra puro vegetal Framboesa e PImenta Rosa 5x90g Caixa | F64: Framboesa e PImenta Rosa | G64: 5 | H64: 90g | I64: Caixa | J64: Puro vegetal \ Nutritivo | K64: 33.9 | L64: 33.9
... B76: Natura | C76: Tododia | D76: Sabonete em barra puro vegetal | E76: =TRIM(CONCATENATE(C76, " ", D76, " ", F76, " ", IF(G76>0, G76 & "x" & H76, H76), " ", I76)) -> Tododia Sabonete em barra puro vegetal Ameixa e flor de baunilha, Ameixa e Flor de Cereja eRroma e Flor de Amora 5x90g Caixa | F76: Ameixa e flor de baunilha, Ameixa e Flor de Cereja eRroma e Flor de Amora | G76: 5 | H76: 90g | I76: Caixa | J76: Puro vegetal \ Nutritivo | K76: 41.9 | L76: 41.9
B77: Natura | C77: Tododia | D77: Sabonete Liquido Intimo | E77: =TRIM(CONCATENATE(C77, " ", D77, " ", F77, " ", IF(G77>0, G77 & "x" & H77, H77), " ", I77)) -> Tododia Sabonete Liquido Intimo Algodão, Suave, Conforto 200ml Frasco | F77: Algodão, Suave, Conforto | H77: 200ml | I77: Frasco | J77: Suave \ Conforto | K77: 49.9 | L77: 49.9
B78: Natura | C78: Tododia | D78: Sabonete Liquido Intimo | E78: =TRIM(CONCATENATE(C78, " ", D78, " ", F78, " ", IF(G78>0, G78 & "x" & H78, H78), " ", I78)) -> Tododia Sabonete Liquido Intimo Cereja e Avelã 200ml Frasco | F78: Cereja e Avelã | H78: 200ml | I78: Frasco | J78: Proteção \ Cuidado | K78: 49.9 | L78: 49.9
B79: Natura | C79: Tododia | D79: Sabonete Liquido Intimo | E79: =TRIM(CONCATENATE(C79, " ", D79, " ", F79, " ", IF(G79>0, G79 & "x" & H79, H79), " ", I79)) -> Tododia Sabonete Liquido Intimo Delicado e Frescor 200ml Frasco | F79: Delicado e Frescor | H79: 200ml | I79: Frasco | J79: Delicado \ Frescor | K79: 49.9 | L79: 49.9
B80: Natura | C80: Tododia | D80: Sabonete Liquido Corpo e Esfoliante | E80: =TRIM(CONCATENATE(C80, " ", D80, " ", F80, " ", IF(G80>0, G80 & "x" & H80, H80), " ", I80)) -> Tododia Sabonete Liquido Corpo e Esfoliante Limão e Hortelã 190g Frasco | F80: Limão e Hortelã | H80: 190g | I80: Frasco | J80: Esfoliante | K80: 49.9 | L80: 49.9
B81: Natura | C81: Tododia | D81: Esfoliante em Creme Corporal | E81: =TRIM(CONCATENATE(C81, " ", D81, " ", F81, " ", IF(G81>0, G81 & "x" & H81, H81), " ", I81)) -> Tododia Esfoliante em Creme Corporal Macadâmia 200ml Frasco | F81: Macadâmia | H81: 200ml | I81: Frasco | J81: Esfoliante | K81: 49.9 | L81: 49.9
B82: Natura | C82: Tododia | D82: Esfoliante em Creme Corporal | E82: =TRIM(CONCATENATE(C82, " ", D82, " ", F82, " ", IF(G82>0, G82 & "x" & H82, H82), " ", I82)) -> Tododia Esfoliante em Creme Corporal Jambo Rosa e Flor de Caju 190g Frasco | F82: Jambo Rosa e Flor de Caju | H82: 190g | I82: Frasco | J82: Esfoliante Nutritivo \ Suaviza \ Perfuma | K82: 49.9 | L82: 49.9
B83: Natura | C83: Tododia | D83: Geleia Desodorante Iluminador | E83: =TRIM(CONCATENATE(C83, " ", D83, " ", F83, " ", IF(G83>0, G83 & "x" & H83, H83), " ", I83)) -> Tododia Geleia Desodorante Iluminador Jambo Rosa e Flor de Caju 100g Frasco | F83: Jambo Rosa e Flor de Caju | H83: 100g | I83: Frasco | J83: Gelia Iluminador \ Desosrante \ Perfuma | K83: R$ 59, 90 | L83: R$ 59, 90
B84: Natura | C84: Tododia | D84: Agua pre-biotica para o corpo | E84: =TRIM(CONCATENATE(C84, " ", D84, " ", F84, " ", IF(G84>0, G84 & "x" & H84, H84), " ", I84)) -> Tododia Agua pre-biotica para o corpo Manga Rosa e Água de Coco 150ml Frasco | F84: Manga Rosa e Água de Coco | H84: 150ml | I84: Frasco | J84: Hidrata e Refresca a Pele | K84: R$ 60, 00 | L84: R$ 60, 00
B85: Natura | C85: Tododia | D85: Bruma Facil | E85: =TRIM(CONCATENATE(C85, " ", D85, " ", F85, " ", IF(G85>0, G85 & "x" & H85, H85), " ", I85)) -> Tododia Bruma Facil Flor de Gengibre e Tangerina 100ml Frasco | F85: Flor de Gengibre e Tangerina | H85: 100ml | I85: Frasco | J85: Energizante \ spray Facil | K85: 49.9 | L85: 49.9
B86: Natura | C86: Tododia | D86: Creme Desodorante | E86: =TRIM(CONCATENATE(C86, " ", D86, " ", F86, " ", IF(G86>0, G86 & "x" & H86, H86), " ", I86)) -> Tododia Creme Desodorante Flor de Gengibre e Tangerina 200ml Frasco | F86: Flor de Gengibre e Tangerina | H86: 200ml | I86: Frasco | J86: 2 em 1 \ Energizante \ Nutritivo | K86: 51.9 | L86: 51.9
B87: Natura | C87: Tododia | D87: Desodorante Antitranspirante Roll-on | E87: =TRIM(CONCATENATE(C87, " ", D87, " ", F87, " ", IF(G87>0, G87 & "x" & H87, H87), " ", I87)) -> Tododia Desodorante Antitranspirante Roll-on Aclarar 70ml Frasco | F87: Aclarar | H87: 70ml | I87: Frasco | K87: 29.9 | L87: 29.9
B88: Natura | C88: Tododia | D88: Desodorante Antitranspirante Roll-on | E88: =TRIM(CONCATENATE(C88, " ", D88, " ", F88, " ", IF(G88>0, G88 & "x" & H88, H88), " ", I88)) -> Tododia Desodorante Antitranspirante Roll-on Algodão 70ml Frasco | F88: Algodão | H88: 70ml | I88: Frasco | K88: 29.9 | L88: 29.9
B89: Natura | C89: Tododia | D89: Desodorante Antitranspirante Roll-on | E89: =TRIM(CONCATENATE(C89, " ", D89, " ", F89, " ", IF(G89>0, G89 & "x" & H89, H89), " ", I89)) -> Tododia Desodorante Antitranspirante Roll-on Alecrim e Salvia 70ml Frasco | F89: Alecrim e Salvia | H89: 70ml | I89: Frasco | J89: Proteção Inv \ 0% Alcool | K89: 29.9 | L89: 29.9
B90: Natura | C90: Tododia | D90: Desodorante Antitranspirante Roll-on | E90: =TRIM(CONCATENATE(C90, " ", D90, " ", F90, " ", IF(G90>0, G90 & "x" & H90, H90), " ", I90)) -> Tododia Desodorante Antitranspirante Roll-on Ameixa e Flor de Baunilha 70ml Frasco | F90: Ameixa e Flor de Baunilha | H90: 70ml | I90: Frasco | J90: Proteção Performace\ Secagem Rapida | K90: 29.9 | L90: 29.9
B91: Natura | C91: Tododia | D91: Desodorante Antitranspirante Roll-on | E91: =TRIM(CONCATENATE(C91, " ", D91, " ", F91, " ", IF(G91>0, G91 & "x" & H91, H91), " ", I91)) -> Tododia Desodorante Antitranspirante Roll-on Amora Vermelha e Jabuticba 70ml Frasco | F91: Amora Vermelha e Jabuticba | H91: 70ml | I91: Frasco | J91: Proteção Performace\ Secagem Rapida | K91: 29.9 | L91: 29.9
B92: Natura | C92: Tododia | D92: Desodorante Antitranspirante Roll-on | E92: =TRIM(CONCATENATE(C92, " ", D92, " ", F92, " ", IF(G92>0, G92 & "x" & H92, H92), " ", I92)) -> Tododia Desodorante Antitranspirante Roll-on Capim Limão e Hortelã 70ml Frasco | F92: Capim Limão e Hortelã | H92: 70ml | I92: Frasco | J92: Proteção Inv \ 0% Alcool | K92: 29.9 | L92: 29.9
B93: Natura | C93: Tododia | D93: Desodorante Antitranspirante Roll-on | E93: =TRIM(CONCATENATE(C93, " ", D93, " ", F93, " ", IF(G93>0, G93 & "x" & H93, H93), " ", I93)) -> Tododia Desodorante Antitranspirante Roll-on Cereja e Avelã 70ml Frasco | F93: Cereja e Avelã | H93: 70ml | I93: Frasco | J93: Proteção Performace\ Secagem Rapida | K93: 29.9 | L93: 29.9
B94: Natura | C94: Tododia | D94: Desodorante Antitranspirante Roll-on | E94: =TRIM(CONCATENATE(C94, " ", D94, " ", F94, " ", IF(G94>0, G94 & "x" & H94, H94), " ", I94)) -> Tododia Desodorante Antitranspirante Roll-on Macadania 70ml Frasco | F94: Macadania | H94: 70ml | I94: Frasco | J94: Proteção Performace\ Secagem Rapida | K94: 29.9 | L94: 29.9
B95: Natura | C95: Tododia | D95: Desodorante Antitranspirante Roll-on | E95: =TRIM(CONCATENATE(C95, " ", D95, " ", F95, " ", IF(G95>0, G95 & "x" & H95, H95), " ", I95)) -> Tododia Desodorante Antitranspirante Roll-on Tamara e Canela 70ml Frasco | F95: Tamara e Canela | H95: 70ml | I95: Frasco | J95: Proteção Performace\ Secagem Rapida | K95: 29.9 | L95: 29.9
B96: Natura | C96: Tododia | D96: Desodorante Antitranspirante Roll-on | E96: =TRIM(CONCATENATE(C96, " ", D96, " ", F96, " ", IF(G96>0, G96 & "x" & H96, H96), " ", I96)) -> Tododia Desodorante Antitranspirante Roll-on Sem Perfume 70ml Frasco | F96: Sem Perfume | H96: 70ml | I96: Frasco | J96: Proteção Performace\ Secagem Rapida | K96: 29.9 | L96: 29.9
B97: Natura | C97: Tododia | D97: Desodorante Creme | E97: =TRIM(CONCATENATE(C97, " ", D97, " ", F97, " ", IF(G97>0, G97 & "x" & H97, H97), " ", I97)) -> Tododia Desodorante Creme Ameixa e Flor de Baunilha 80g Frasco | F97: Ameixa e Flor de Baunilha | H97: 80g | I97: Frasco | J97: Proteção Inv \ 0% Alcool \ Performace | K97: 30.9 | L97: 30.9
B98: Natura | C98: Tododia | D98: Desodorante Creme | E98: =TRIM(CONCATENATE(C98, " ", D98, " ", F98, " ", IF(G98>0, G98 & "x" & H98, H98), " ", I98)) -> Tododia Desodorante Creme Cereja e Avela 80g Frasco | F98: Cereja e Avela | H98: 80g | I98: Frasco | J98: Proteção Inv \ 0% Alcool \ Performace | K98: 30.9 | L98: 30.9
B99: Natura | C99: Tododia | D99: Desodorante Creme | E99: =TRIM(CONCATENATE(C99, " ", D99, " ", F99, " ", IF(G99>0, G99 & "x" & H99, H99), " ", I99)) -> Tododia Desodorante Creme Invisível 80g Frasco | F99: Invisível | H99: 80g | I99: Frasco | J99: Proteção Inv \ 0% Alcool \ Performace | K99: 30.9 | L99: 30.9
B100: Natura | C100: Tododia | D100: Desodorante Creme | E100: =TRIM(CONCATENATE(C100, " ", D100, " ", F100, " ", IF(G100>0, G100 & "x" & H100, H100), " ", I100)) -> Tododia Desodorante Creme Leite de Algodao 80g Frasco | F100: Leite de Algodao | H100: 80g | I100: Frasco | J100: Proteção Inv \ 0% Alcool \ Performace | K100: 30.9 | L100: 30.9
... B110: Natura | C110: Tododia | D110: Creme Para Maos e Pes | E110: =TRIM(CONCATENATE(C110, " ", D110, " ", F110, " ", IF(G110>0, G110 & "x" & H110, H110), " ", I110)) -> Tododia Creme Para Maos e Pes Noz Pecã e Cacau (Com Desodorante) 50ml Frasco | F110: Noz Pecã e Cacau (Com Desodorante) | H110: 50ml | I110: Frasco | J110: Com desodorante para os pés | K110: 36.9 | L110: 36.9
B111: Natura | C111: Tododia | D111: Sabonete Liquido em Gel | E111: =TRIM(CONCATENATE(C111, " ", D111, " ", F111, " ", IF(G111>0, G111 & "x" & H111, H111), " ", I111)) -> Tododia Sabonete Liquido em Gel Algodão 300ml Frasco | F111: Algodão | H111: 300ml | I111: Frasco | J111: Cremoso \ Perfume \ Hidrata | K111: R$ 49,90 | L111: R$ 49,90
B112: Natura | C112: Tododia | D112: Sabonete Liquido em Gel | E112: =TRIM(CONCATENATE(C112, " ", D112, " ", F112, " ", IF(G112>0, G112 & "x" & H112, H112), " ", I112)) -> Tododia Sabonete Liquido em Gel Alecrim e Salvia 300ml Frasco | F112: Alecrim e Salvia | H112: 300ml | I112: Frasco | J112: Cremoso \ Perfume \ Hidrata | K112: R$ 49,90 | L112: R$ 49,90
B113: Natura | C113: Tododia | D113: Sabonete Liquido em Gel | E113: =TRIM(CONCATENATE(C113, " ", D113, " ", F113, " ", IF(G113>0, G113 & "x" & H113, H113), " ", I113)) -> Tododia Sabonete Liquido em Gel Alecrim e Salvia 390g Frasco | F113: Alecrim e Salvia | H113: 390g | I113: Frasco | J113: Cremoso \ Perfume \ Hidrata | K113: R$ 49,91 | L113: R$ 49,91
B114: Natura | C114: Tododia | D114: Sabonete Liquido em Gel | E114: =TRIM(CONCATENATE(C114, " ", D114, " ", F114, " ", IF(G114>0, G114 & "x" & H114, H114), " ", I114)) -> Tododia Sabonete Liquido em Gel Ameixa e Flor de Baunilha 300ml Frasco | F114: Ameixa e Flor de Baunilha | H114: 300ml | I114: Frasco | J114: Cremoso \ Perfume \ Hidrata | K114: R$ 49,90 | L114: R$ 49,90
B115: Natura | C115: Tododia | D115: Sabonete Liquido em Gel | E115: =TRIM(CONCATENATE(C115, " ", D115, " ", F115, " ", IF(G115>0, G115 & "x" & H115, H115), " ", I115)) -> Tododia Sabonete Liquido em Gel Amora Vermelha e Jabuticaba 300ml Frasco | F115: Amora Vermelha e Jabuticaba | H115: 300ml | I115: Frasco | J115: Cremoso \ Perfume \ Hidrata | K115: R$ 49,90 | L115: R$ 49,90
B116: Natura | C116: Tododia | D116: Sabonete Liquido em Gel | E116: =TRIM(CONCATENATE(C116, " ", D116, " ", F116, " ", IF(G116>0, G116 & "x" & H116, H116), " ", I116)) -> Tododia Sabonete Liquido em Gel Cereja e Avelã 300ml Frasco | F116: Cereja e Avelã | H116: 300ml | I116: Frasco | J116: Cremoso \ Perfume \ Hidrata | K116: R$ 49,90 | L116: R$ 49,90
B117: Natura | C117: Tododia | D117: Sabonete Liquido em Gel | E117: =TRIM(CONCATENATE(C117, " ", D117, " ", F117, " ", IF(G117>0, G117 & "x" & H117, H117), " ", I117)) -> Tododia Sabonete Liquido em Gel Chá de Camomila e Lavanda 300ml Frasco | F117: Chá de Camomila e Lavanda | H117: 300ml | I117: Frasco | J117: Banho nas Nuvens | K117: R$ 49,90 | L117: R$ 49,90
B118: Natura | C118: Tododia | D118: Sabonete Liquido em Gel | E118: =TRIM(CONCATENATE(C118, " ", D118, " ", F118, " ", IF(G118>0, G118 & "x" & H118, H118), " ", I118)) -> Tododia Sabonete Liquido em Gel Flor de Gengibre e Tangerina 300ml Frasco | F118: Flor de Gengibre e Tangerina | H118: 300ml | I118: Frasco | J118: Banho Energizante | K118: R$ 49,90 | L118: R$ 49,90
B119: Natura | C119: Tododia | D119: Sabonete Liquido em Gel | E119: =TRIM(CONCATENATE(C119, " ", D119, " ", F119, " ", IF(G119>0, G119 & "x" & H119, H119), " ", I119)) -> Tododia Sabonete Liquido em Gel Macadamia 300ml Frasco | F119: Macadamia | H119: 300ml | I119: Frasco | J119: Cremoso \ Perfume \ Hidrata | K119: R$ 49,90 | L119: R$ 49,90
B120: Natura | C120: Tododia | D120: Sabonete Liquido em Gel | E120: =TRIM(CONCATENATE(C120, " ", D120, " ", F120, " ", IF(G120>0, G120 & "x" & H120, H120), " ", I120)) -> Tododia Sabonete Liquido em Gel Noz Pecã e Cacau 300ml Frasco | F120: Noz Pecã e Cacau | H120: 300ml | I120: Frasco | J120: Cremoso \ Perfume \ Hidrata | K120: R$ 49,90 | L120: R$ 49,90
B121: Natura | C121: Tododia | D121: Sabonete Liquido em Gel | E121: =TRIM(CONCATENATE(C121, " ", D121, " ", F121, " ", IF(G121>0, G121 & "x" & H121, H121), " ", I121)) -> Tododia Sabonete Liquido em Gel Tamara e Canela 300ml Frasco | F121: Tamara e Canela | H121: 300ml | I121: Frasco | J121: Cremoso \ Perfume \ Hidrata | K121: R$ 49,90 | L121: R$ 49,90
B122: Natura | C122: Tododia | D122: Sabonete Liquido em Gel | E122: =TRIM(CONCATENATE(C122, " ", D122, " ", F122, " ", IF(G122>0, G122 & "x" & H122, H122), " ", I122)) -> Tododia Sabonete Liquido em Gel Algodão 300ml Refil | F122: Algodão | H122: 300ml | I122: Refil | J122: Cremoso \ Perfume \ Hidrata | K122: R$: 37,90 | L122: R$: 37,90
B123: Natura | C123: Tododia | D123: Sabonete Liquido em Gel | E123: =TRIM(CONCATENATE(C123, " ", D123, " ", F123, " ", IF(G123>0, G123 & "x" & H123, H123), " ", I123)) -> Tododia Sabonete Liquido em Gel Alecrim e Salvia 300ml Refil | F123: Alecrim e Salvia | H123: 300ml | I123: Refil | J123: Cremoso \ Perfume \ Hidrata | K123: R$: 37,90 | L123: R$: 37,90
B124: Natura | C124: Tododia | D124: Sabonete Liquido em Gel | E124: =TRIM(CONCATENATE(C124, " ", D124, " ", F124, " ", IF(G124>0, G124 & "x" & H124, H124), " ", I124)) -> Tododia Sabonete Liquido em Gel Alecrim e Salvia 300ml Refil | F124: Alecrim e Salvia | H124: 300ml | I124: Refil | J124: Corpo e Mãos | K124: 58.9 | L124: 58.9
B125: Natura | C125: Tododia | D125: Sabonete Liquido em Gel | E125: =TRIM(CONCATENATE(C125, " ", D125, " ", F125, " ", IF(G125>0, G125 & "x" & H125, H125), " ", I125)) -> Tododia Sabonete Liquido em Gel Ameixa e Flor de Baunilha 300ml Refil | F125: Ameixa e Flor de Baunilha | H125: 300ml | I125: Refil | J125: Cremoso \ Perfume \ Hidrata | K125: R$: 37,90 | L125: R$: 37,90
B126: Natura | C126: Tododia | D126: Sabonete Liquido em Gel | E126: =TRIM(CONCATENATE(C126, " ", D126, " ", F126, " ", IF(G126>0, G126 & "x" & H126, H126), " ", I126)) -> Tododia Sabonete Liquido em Gel Amora Vermelha e Jabuticaba 300ml Refil | F126: Amora Vermelha e Jabuticaba | H126: 300ml | I126: Refil | J126: Cremoso \ Perfume \ Hidrata | K126: R$: 37,90 | L126: R$: 37,90
B127: Natura | C127: Tododia | D127: Sabonete Liquido em Gel | E127: =TRIM(CONCATENATE(C127, " ", D127, " ", F127, " ", IF(G127>0, G127 & "x" & H127, H127), " ", I127)) -> Tododia Sabonete Liquido em Gel Cereja e Avelã 300ml Refil | F127: Cereja e Avelã | H127: 300ml | I127: Refil | J127: Cremoso \ Perfume \ Hidrata | K127: R$: 37,90 | L127: R$: 37,90
...

Sheet Movimento
A1: Data | B1: COD do Produto | C1: Produto | D1: Cliente | E1: Tipo de Movimentação | F1: Quantidade | G1: Preço Custo Total | H1: Preço Venda Total | I1: Observações | J1: Status | K1: Data Prevista | L1: Tipo de Pagamento | M1: ID_Venda
A2: 45963.238 | B2: 1 | C2: Natura Hidrante Desodorante Corporal Tododia Algodão 400ml Frasco | D2: ASD | E2: SAÍDA | F2: -1 | G2: -76 | H2: 180 | I2: ASDASDSAD | J2: PAGO | K2: 45963.238 | L2: Pix | M2: V-23A77E
A3: 45963.245 | B3: 1 | C3: Natura Hidrante Desodorante Corporal Tododia Algodão 400ml Frasco | D3: GHHHH | E3: SAÍDA | F3: -1 | G3: -76 | H3: 180 | I3: aa | J3: PAGO | K3: 45963.245 | L3: Pix | M3: V-A4BAD1
A4: 45963.247 | B4: 1 | C4: Natura Hidrante Desodorante Corporal Tododia Algodão 400ml Frasco | D4: ASDDAS | E4: SAÍDA | F4: 0 | G4: 0 | H4: 90 | I4: Parcela 1/2 | J4: A RECEBER | K4: 45963 | L4: Parcelado | M4: V-4F0824
A5: 45963.247 | B5: 1 | C5: Natura Hidrante Desodorante Corporal Tododia Algodão 400ml Frasco | D5: ASDDAS | E5: SAÍDA | F5: -1 | G5: -76 | H5: 90 | I5: Parcela 2/2 | J5: A RECEBER | K5: 45993 | L5: Parcelado | M5: V-4F0824
A6: 45963.251 | B6: 2 | C6: Natura Hidrante Desodorante Corporal Tododia Ameixa e Flor de Baunilha 400ml Frasco | D6: GHHHH | E6: SAÍDA | F6: 0 | G6: 0 | H6: 229 | I6: Parcela 1/2 | a | J6: A RECEBER | K6: 45963 | L6: Parcelado | M6: V-059D98
A7: 45963.251 | B7: 2 | C7: Natura Hidrante Desodorante Corporal Tododia Ameixa e Flor de Baunilha 400ml Frasco | D7: GHHHH | E7: SAÍDA | F7: -1 | G7: -75.9 | H7: 229 | I7: Parcela 2/2 | a | J7: A RECEBER | K7: 45993 | L7: Parcelado | M7: V-059D98
A8: 45963.251 | B8: 1 | C8: Natura Hidrante Desodorante Corporal Tododia Algodão 400ml Frasco | D8: GHHHH | E8: SAÍDA | F8: 0 | G8: 0 | H8: 229 | I8: Parcela 1/2 | a | J8: A RECEBER | K8: 45963 | L8: Parcelado | M8: V-059D98
A9: 45963.251 | B9: 1 | C9: Natura Hidrante Desodorante Corporal Tododia Algodão 400ml Frasco | D9: GHHHH | E9: SAÍDA | F9: -1 | G9: -76 | H9: 229 | I9: Parcela 2/2 | a | J9: A RECEBER | K9: 45993 | L9: Parcelado | M9: V-059D98
A10: 45963.265 | B10: 1 | C10: Natura Hidrante Desodorante Corporal Tododia Algodão 400ml Frasco | D10: Natura | E10: ENTRADA | F10: 3 | G10: 228 | H10: 540 | J10: PAGO | K10: 45964 | L10: Pix | M10: E-766FE7
A11: 45963.266 | B11: 1 | C11: Natura Hidrante Desodorante Corporal Tododia Algodão 400ml Frasco | D11: Natura | E11: ENTRADA | F11: 5 | G11: 380 | H11: 900 | I11: Ciclo 26 | J11: PAGO | K11: 45964 | L11: Pix | M11: E-37A388
A12: 45963.278 | B12: 2 | C12: Natura Hidrante Desodorante Corporal Tododia Ameixa e Flor de Baunilha 400ml Frasco | D12: ASD | E12: SAÍDA | F12: -1 | G12: -75.9 | H12: 278 | J12: PAGO | K12: 45963.278 | L12: Pix | M12: V-DA3106
A13: 45963.278 | B13: 1 | C13: Natura Hidrante Desodorante Corporal Tododia Algodão 400ml Frasco | D13: ASD | E13: SAÍDA | F13: -1 | G13: -76 | H13: 180 | I13: 1 | J13: A RECEBER | K13: 45963 | L13: Fiado | M13: V-1567C2
A14: 45963.303 | B14: 2 | C14: Natura Hidrante Desodorante Corporal Tododia Ameixa e Flor de Baunilha 400ml Frasco | D14: Natura | E14: ENTRADA | F14: 6 | G14: 455.4 | H14: 1668 | J14: PAGO | K14: 2025-11-02 23:59:59 | L14: Pix | M14: E-BF13D6

Sheet Clientes
A1: ID_Cliente | B1: Nome | C1: Telefone | D1: Email | E1: Endereço | F1: Observações
A2: C-C2BFEE | B2: ASD | C2: 11 92393287 | D2: dsadsa@gmail.com | E2: Cachoeira | F2: Loja Whats
A3: C-4C4B74 | B3: ASDDAS | C3: 2232 | D3: sadlapsd@gmail.com | E3: Furnas | F3: Site
A4: C-0947A0 | B4: FGGH | C4: asdasd | D4: asdasd | E4: asd | F4: dasda
A5: C-7482A8 | B5: GHHHH | F5: Cadastrado via Venda

Sheet Relatorio
A1: FATURAMENTO BRUTO | B1: =SUMIFS(Movimento!H:H, Movimento!E:E, "SAÍDA", Movimento!J:J, "PAGO") -> 638
A2: CUSTO DE MERCADORIA VENDIDA (CMV) | B2: =SUMIFS(Movimento!G:G, Movimento!E:E, "SAÍDA") * -1 -> 531.8
A3: LUCRO BRUTO TOTAL | B3: =B1 - B2 -> 106.2
A4: MARGEM BRUTA (%) | B4: =(B3 / B1) -> 0.16645768
A5: QTD PRODUTOS FIADO | B5: =SUMIFS(Movimento!F:F, Movimento!J:J, "A RECEBER") * -1 -> 4
A6: VALOR A RECEBER (FIADO) | B6: =SUMIFS(Movimento!H:H, Movimento!J:J, "A RECEBER") -> 1276
A7: ESTOQUE TOTAL (ITENS) | B7: =SUM(Movimento!F:F) -> 7
A8: CUSTO TOTAL DO ESTOQUE ATUAL | B8: =SUM(Movimento!G:G) -> 531.6
A9: SALDO DE CAIXA DO ESTOQUE | B9: =B1- B8 -> 106.4
